{
    "command": "\n                    await bot1.chat('hello!!!!!!!!!!!');\n                    await bot1.chat('/gamerule doMobSpawning false');\n                    await bot1.chat('/gamerule randomTickSpeed 0');\n                    \n                    await bot3.chat('/gamemode spectator');\n                    await bot3.chat('/tp @p 10 10 10');\n                    await bot1.chat('/forceload add 4281 1129');\n                    await bot4.chat('/setblock 4284 67 1126 minecraft:barrier');\n                    await bot4.chat('/gamemode spectator');\n                    await bot4.chat('/tp @p 4284 68 1126 -90 90');\n                await bot1.chat('/fill 4282 63 1124 4286 63 1128 minecraft:glass');await bot1.chat('/fill 4281 64 1123 4286 65 1128 minecraft:air');await bot1.chat('/setblock 4284 65 1126 minecraft:bricks');await bot1.chat('/setblock 4284 64 1126 minecraft:oak_planks');await bot1.chat('/setblock 4283 64 1126 minecraft:sponge');await bot1.chat('/setblock 4284 64 1125 minecraft:bricks');await bot1.chat('/setblock 4283 64 1125 minecraft:pumpkin');await bot1.chat('/tp @p 4284.92 65 1120.78 43.07 7.91 ');await bot1.chat('/give @p oak_planks 5');await bot1.chat('/give @p pumpkin 4');await bot1.chat('/give @p bricks 1');await bot2.chat('/tp @p 4285.23 65 1120.41 67.26 6.43 ');await bot2.chat('/give @p sponge 4');await bot2.chat('/give @p bricks 2');",
    "obs_command": [
        [
            "\n                    await bot4.chat('/setblock 4278 63 1126 minecraft:barrier');\n                    await bot4.chat('/tp @p 4278 64 1126 -90 0');\n                "
        ],
        [
            "\n                    await bot4.chat('/setblock 4284 63 1132 minecraft:barrier');\n                    await bot4.chat('/tp @p 4284 64 1132 -180 0');\n                "
        ],
        [
            "\n                    await bot4.chat('/tp @p 4284 68 1126 -90 90');\n                "
        ],
        [
            "await bot1.chat('/fill 4281 64 1123 4286 65 1128 minecraft:air');"
        ]
    ],
    "variant": 100001,
    "actions": [
        [],
        [],
        []
    ],
    "done_input": [
        [
            "bricks",
            4284,
            65,
            1126
        ],
        [
            "oak_planks",
            4284,
            64,
            1126
        ],
        [
            "sponge",
            4283,
            64,
            1126
        ],
        [
            "bricks",
            4284,
            64,
            1125
        ],
        [
            "pumpkin",
            4283,
            64,
            1125
        ]
    ],
    "bot1": {
        "location": [
            4284.92,
            65,
            1120.78
        ],
        "rotation": [
            43.07,
            7.91
        ],
        "inventory": {
            "oak_planks": 5,
            "pumpkin": 4,
            "bricks": 1
        }
    },
    "bot2": {
        "location": [
            4285.23,
            65,
            1120.41
        ],
        "rotation": [
            67.26,
            6.43
        ],
        "inventory": {
            "sponge": 4,
            "bricks": 2
        }
    },
    "item_spots": {},
    "variants_config": {
        "agent_counts": [
            2
        ],
        "background": [
            "minecraft:glass"
        ],
        "playground_location": {
            "name": "swamp",
            "x": [
                4282,
                4286
            ],
            "z": [
                1124,
                1128
            ],
            "y": 64,
            "bot_range": [
                [
                    4283,
                    4286
                ],
                [
                    1116,
                    1122
                ],
                65
            ],
            "center": [
                4284,
                64,
                1126
            ]
        },
        "base_shape": [
            [
                2,
                2,
                2
            ]
        ],
        "block_type": [
            "bricks",
            "oak_planks",
            "sponge",
            "bricks",
            "pumpkin"
        ],
        "placement_shape": [
            [
                1,
                1,
                1
            ],
            [
                1,
                0,
                1
            ],
            [
                0,
                0,
                1
            ],
            [
                1,
                0,
                0
            ],
            [
                0,
                0,
                0
            ]
        ],
        "block_count": 5,
        "placement_shape_number": [
            7,
            3,
            2,
            1,
            0
        ]
    },
    "bot_list": [
        "bot1",
        "bot2"
    ],
    "center_position": [
        4284,
        64,
        1126
    ]
}