{
    "command": "\n                    await bot1.chat('hello!!!!!!!!!!!');\n                    await bot1.chat('/gamerule doMobSpawning false');\n                    await bot1.chat('/gamerule randomTickSpeed 0');\n                    \n                    await bot3.chat('/gamemode spectator');\n                    await bot3.chat('/tp @p 10 10 10');\n                    await bot1.chat('/forceload add 11668 8491');\n                    await bot4.chat('/setblock 11671 109 8488 minecraft:barrier');\n                    await bot4.chat('/gamemode spectator');\n                    await bot4.chat('/tp @p 11671 110 8488 -90 90');\n                await bot1.chat('/fill 11669 105 8486 11673 105 8490 minecraft:smooth_quartz');await bot1.chat('/fill 11668 106 8485 11673 107 8490 minecraft:air');await bot1.chat('/setblock 11672 107 8487 minecraft:oak_log');await bot1.chat('/setblock 11670 107 8487 minecraft:clay');await bot1.chat('/setblock 11673 106 8487 minecraft:end_stone');await bot1.chat('/setblock 11672 106 8487 minecraft:bricks');await bot1.chat('/setblock 11670 106 8487 minecraft:stone');await bot1.chat('/tp @p 11668.07 108 8494.2 20.84 -7.54 ');await bot1.chat('/give @p end_stone 4');await bot1.chat('/give @p stone 4');await bot1.chat('/give @p clay 1');await bot2.chat('/tp @p 11668.63 108 8495.44 252.21 4.73 ');await bot2.chat('/give @p bricks 2');await bot2.chat('/give @p oak_log 3');await bot2.chat('/give @p stone 1');await bot2.chat('/give @p end_stone 2');",
    "obs_command": [
        [
            "\n                    await bot4.chat('/setblock 11665 105 8488 minecraft:barrier');\n                    await bot4.chat('/tp @p 11665 106 8488 -90 0');\n                "
        ],
        [
            "\n                    await bot4.chat('/setblock 11671 105 8494 minecraft:barrier');\n                    await bot4.chat('/tp @p 11671 106 8494 -180 0');\n                "
        ],
        [
            "\n                    await bot4.chat('/tp @p 11671 110 8488 -90 90');\n                "
        ],
        [
            "await bot1.chat('/fill 11668 106 8485 11673 107 8490 minecraft:air');"
        ]
    ],
    "variant": 100008,
    "actions": [
        [],
        [],
        []
    ],
    "done_input": [
        [
            "oak_log",
            11672,
            107,
            8487
        ],
        [
            "clay",
            11670,
            107,
            8487
        ],
        [
            "end_stone",
            11673,
            106,
            8487
        ],
        [
            "bricks",
            11672,
            106,
            8487
        ],
        [
            "stone",
            11670,
            106,
            8487
        ]
    ],
    "bot1": {
        "location": [
            11668.07,
            108,
            8494.2
        ],
        "rotation": [
            20.84,
            -7.54
        ],
        "inventory": {
            "end_stone": 4,
            "stone": 4,
            "clay": 1
        }
    },
    "bot2": {
        "location": [
            11668.63,
            108,
            8495.44
        ],
        "rotation": [
            252.21,
            4.73
        ],
        "inventory": {
            "bricks": 2,
            "oak_log": 3,
            "stone": 1,
            "end_stone": 2
        }
    },
    "item_spots": {},
    "variants_config": {
        "agent_counts": [
            2
        ],
        "background": [
            "minecraft:smooth_quartz"
        ],
        "playground_location": {
            "name": "snow_mountain",
            "x": [
                11669,
                11673
            ],
            "z": [
                8486,
                8490
            ],
            "y": 106,
            "bot_range": [
                [
                    11668,
                    11673
                ],
                [
                    8494,
                    8496
                ],
                108
            ],
            "center": [
                11671,
                106,
                8488
            ]
        },
        "base_shape": [
            [
                4,
                1,
                2
            ]
        ],
        "block_type": [
            "oak_log",
            "clay",
            "end_stone",
            "bricks",
            "stone"
        ],
        "placement_shape": [
            [
                2,
                1,
                0
            ],
            [
                0,
                1,
                0
            ],
            [
                3,
                0,
                0
            ],
            [
                2,
                0,
                0
            ],
            [
                0,
                0,
                0
            ]
        ],
        "block_count": 5,
        "placement_shape_number": [
            6,
            4,
            3,
            2,
            0
        ]
    },
    "bot_list": [
        "bot1",
        "bot2"
    ],
    "center_position": [
        11671,
        106,
        8488
    ]
}