{
    "command": "\n                    await bot1.chat('hello!!!!!!!!!!!');\n                    await bot1.chat('/gamerule doMobSpawning false');\n                    await bot1.chat('/gamerule randomTickSpeed 0');\n                    \n                    await bot3.chat('/gamemode spectator');\n                    await bot3.chat('/tp @p 10 10 10');\n                    await bot1.chat('/forceload add 11668 8491');\n                    await bot4.chat('/setblock 11671 109 8488 minecraft:barrier');\n                    await bot4.chat('/gamemode spectator');\n                    await bot4.chat('/tp @p 11671 110 8488 -90 90');\n                await bot1.chat('/fill 11669 105 8486 11673 105 8490 minecraft:obsidian');await bot1.chat('/fill 11668 106 8485 11673 107 8490 minecraft:air');await bot1.chat('/setblock 11670 107 8488 minecraft:purple_wool');await bot1.chat('/setblock 11671 106 8489 minecraft:birch_log');await bot1.chat('/setblock 11670 106 8489 minecraft:bookshelf');await bot1.chat('/setblock 11671 106 8488 minecraft:pumpkin');await bot1.chat('/setblock 11670 106 8488 minecraft:dirt');await bot1.chat('/tp @p 11672.96 108 8495.31 30.91 8.79 ');await bot1.chat('/give @p birch_log 1');await bot1.chat('/give @p dirt 2');await bot1.chat('/give @p purple_wool 4');await bot1.chat('/give @p bookshelf 1');await bot2.chat('/tp @p 11671.02 108 8494.85 311.05 7.41 ');await bot2.chat('/give @p bookshelf 6');await bot2.chat('/give @p pumpkin 4');await bot2.chat('/give @p birch_log 1');await bot2.chat('/give @p purple_wool 1');await bot2.chat('/give @p dirt 3');",
    "obs_command": [
        [
            "\n                    await bot4.chat('/setblock 11665 105 8488 minecraft:barrier');\n                    await bot4.chat('/tp @p 11665 106 8488 -90 0');\n                "
        ],
        [
            "\n                    await bot4.chat('/setblock 11671 105 8494 minecraft:barrier');\n                    await bot4.chat('/tp @p 11671 106 8494 -180 0');\n                "
        ],
        [
            "\n                    await bot4.chat('/tp @p 11671 110 8488 -90 90');\n                "
        ],
        [
            "await bot1.chat('/fill 11668 106 8485 11673 107 8490 minecraft:air');"
        ]
    ],
    "variant": 100009,
    "actions": [
        [],
        [],
        []
    ],
    "done_input": [
        [
            "purple_wool",
            11670,
            107,
            8488
        ],
        [
            "birch_log",
            11671,
            106,
            8489
        ],
        [
            "bookshelf",
            11670,
            106,
            8489
        ],
        [
            "pumpkin",
            11671,
            106,
            8488
        ],
        [
            "dirt",
            11670,
            106,
            8488
        ]
    ],
    "bot1": {
        "location": [
            11672.96,
            108,
            8495.31
        ],
        "rotation": [
            30.91,
            8.79
        ],
        "inventory": {
            "birch_log": 1,
            "dirt": 2,
            "purple_wool": 4,
            "bookshelf": 1
        }
    },
    "bot2": {
        "location": [
            11671.02,
            108,
            8494.85
        ],
        "rotation": [
            311.05,
            7.41
        ],
        "inventory": {
            "bookshelf": 6,
            "pumpkin": 4,
            "birch_log": 1,
            "purple_wool": 1,
            "dirt": 3
        }
    },
    "item_spots": {},
    "variants_config": {
        "agent_counts": [
            2
        ],
        "background": [
            "minecraft:obsidian"
        ],
        "playground_location": {
            "name": "snow_mountain",
            "x": [
                11669,
                11673
            ],
            "z": [
                8486,
                8490
            ],
            "y": 106,
            "bot_range": [
                [
                    11668,
                    11673
                ],
                [
                    8494,
                    8496
                ],
                108
            ],
            "center": [
                11671,
                106,
                8488
            ]
        },
        "base_shape": [
            [
                2,
                3,
                2
            ]
        ],
        "block_type": [
            "purple_wool",
            "birch_log",
            "bookshelf",
            "pumpkin",
            "dirt"
        ],
        "placement_shape": [
            [
                0,
                1,
                1
            ],
            [
                1,
                0,
                2
            ],
            [
                0,
                0,
                2
            ],
            [
                1,
                0,
                1
            ],
            [
                0,
                0,
                1
            ]
        ],
        "block_count": 5,
        "placement_shape_number": [
            8,
            5,
            4,
            3,
            2
        ]
    },
    "bot_list": [
        "bot1",
        "bot2"
    ],
    "center_position": [
        11671,
        106,
        8488
    ]
}