{
    "command": "\n                    await bot1.chat('hello!!!!!!!!!!!');\n                    await bot1.chat('/gamerule doMobSpawning false');\n                    await bot1.chat('/gamerule randomTickSpeed 0');\n                    \n                    await bot3.chat('/gamemode spectator');\n                    await bot3.chat('/tp @p 10 10 10');\n                    await bot1.chat('/forceload add 4281 1129');\n                    await bot4.chat('/setblock 4284 67 1126 minecraft:barrier');\n                    await bot4.chat('/gamemode spectator');\n                    await bot4.chat('/tp @p 4284 68 1126 -90 90');\n                await bot1.chat('/fill 4282 63 1124 4286 63 1128 minecraft:glass');await bot1.chat('/fill 4281 64 1123 4286 65 1128 minecraft:air');await bot1.chat('/setblock 4283 65 1125 minecraft:sponge');await bot1.chat('/setblock 4286 64 1125 minecraft:oak_log');await bot1.chat('/setblock 4285 64 1125 minecraft:bricks');await bot1.chat('/setblock 4284 64 1125 minecraft:acacia_fence');await bot1.chat('/setblock 4283 64 1125 minecraft:iron_ore');await bot1.chat('/tp @p 4285.77 65 1121.44 51.41 -6.88 ');await bot1.chat('/give @p oak_log 5');await bot1.chat('/give @p iron_ore 3');await bot1.chat('/give @p sponge 6');await bot1.chat('/give @p bricks 1');await bot1.chat('/give @p acacia_fence 3');await bot2.chat('/tp @p 4283.48 65 1118.02 32.54 -3.48 ');await bot2.chat('/give @p bricks 2');await bot2.chat('/give @p acacia_fence 4');await bot2.chat('/give @p iron_ore 2');",
    "obs_command": [
        [
            "\n                    await bot4.chat('/setblock 4278 63 1126 minecraft:barrier');\n                    await bot4.chat('/tp @p 4278 64 1126 -90 0');\n                "
        ],
        [
            "\n                    await bot4.chat('/setblock 4284 63 1132 minecraft:barrier');\n                    await bot4.chat('/tp @p 4284 64 1132 -180 0');\n                "
        ],
        [
            "\n                    await bot4.chat('/tp @p 4284 68 1126 -90 90');\n                "
        ],
        [
            "await bot1.chat('/fill 4281 64 1123 4286 65 1128 minecraft:air');"
        ]
    ],
    "variant": 100011,
    "actions": [
        [],
        [],
        []
    ],
    "done_input": [
        [
            "sponge",
            4283,
            65,
            1125
        ],
        [
            "oak_log",
            4286,
            64,
            1125
        ],
        [
            "bricks",
            4285,
            64,
            1125
        ],
        [
            "acacia_fence",
            4284,
            64,
            1125
        ],
        [
            "iron_ore",
            4283,
            64,
            1125
        ]
    ],
    "bot1": {
        "location": [
            4285.77,
            65,
            1121.44
        ],
        "rotation": [
            51.41,
            -6.88
        ],
        "inventory": {
            "oak_log": 5,
            "iron_ore": 3,
            "sponge": 6,
            "bricks": 1,
            "acacia_fence": 3
        }
    },
    "bot2": {
        "location": [
            4283.48,
            65,
            1118.02
        ],
        "rotation": [
            32.54,
            -3.48
        ],
        "inventory": {
            "bricks": 2,
            "acacia_fence": 4,
            "iron_ore": 2
        }
    },
    "item_spots": {},
    "variants_config": {
        "agent_counts": [
            2
        ],
        "background": [
            "minecraft:glass"
        ],
        "playground_location": {
            "name": "swamp",
            "x": [
                4282,
                4286
            ],
            "z": [
                1124,
                1128
            ],
            "y": 64,
            "bot_range": [
                [
                    4283,
                    4286
                ],
                [
                    1116,
                    1122
                ],
                65
            ],
            "center": [
                4284,
                64,
                1126
            ]
        },
        "base_shape": [
            [
                4,
                1,
                2
            ]
        ],
        "block_type": [
            "sponge",
            "oak_log",
            "bricks",
            "acacia_fence",
            "iron_ore"
        ],
        "placement_shape": [
            [
                0,
                1,
                0
            ],
            [
                3,
                0,
                0
            ],
            [
                2,
                0,
                0
            ],
            [
                1,
                0,
                0
            ],
            [
                0,
                0,
                0
            ]
        ],
        "block_count": 5,
        "placement_shape_number": [
            4,
            3,
            2,
            1,
            0
        ]
    },
    "bot_list": [
        "bot1",
        "bot2"
    ],
    "center_position": [
        4284,
        64,
        1126
    ]
}