{
    "command": "\n                    await bot1.chat('hello!!!!!!!!!!!');\n                    await bot1.chat('/gamerule doMobSpawning false');\n                    await bot1.chat('/gamerule randomTickSpeed 0');\n                    \n                    await bot3.chat('/gamemode spectator');\n                    await bot3.chat('/tp @p 10 10 10');\n                    await bot1.chat('/forceload add 4258 164');\n                    await bot4.chat('/setblock 4261 77 161 minecraft:barrier');\n                    await bot4.chat('/gamemode spectator');\n                    await bot4.chat('/tp @p 4261 78 161 -90 90');\n                await bot1.chat('/fill 4259 73 159 4263 73 163 minecraft:oak_wood');await bot1.chat('/fill 4258 74 158 4263 75 163 minecraft:air');await bot1.chat('/setblock 4262 75 160 minecraft:grass_block');await bot1.chat('/setblock 4261 75 160 minecraft:bookshelf');await bot1.chat('/setblock 4262 74 160 minecraft:oak_planks');await bot1.chat('/setblock 4261 74 160 minecraft:bookshelf');await bot1.chat('/setblock 4260 74 160 minecraft:iron_ore');await bot1.chat('/tp @p 4264.23 75 156.15 343.97 2.81 ');await bot1.chat('/give @p oak_planks 3');await bot1.chat('/give @p iron_ore 4');await bot1.chat('/give @p grass_block 3');await bot1.chat('/give @p bookshelf 6');await bot2.chat('/tp @p 4263.32 75 158.92 172.37 -2.98 ');await bot2.chat('/give @p bookshelf 4');await bot2.chat('/give @p oak_planks 2');await bot2.chat('/give @p grass_block 2');",
    "obs_command": [
        [
            "\n                    await bot4.chat('/setblock 4255 73 161 minecraft:barrier');\n                    await bot4.chat('/tp @p 4255 74 161 -90 0');\n                "
        ],
        [
            "\n                    await bot4.chat('/setblock 4261 73 167 minecraft:barrier');\n                    await bot4.chat('/tp @p 4261 74 167 -180 0');\n                "
        ],
        [
            "\n                    await bot4.chat('/tp @p 4261 78 161 -90 90');\n                "
        ],
        [
            "await bot1.chat('/fill 4258 74 158 4263 75 163 minecraft:air');"
        ]
    ],
    "variant": 100013,
    "actions": [
        [],
        [],
        []
    ],
    "done_input": [
        [
            "grass_block",
            4262,
            75,
            160
        ],
        [
            "bookshelf",
            4261,
            75,
            160
        ],
        [
            "oak_planks",
            4262,
            74,
            160
        ],
        [
            "bookshelf",
            4261,
            74,
            160
        ],
        [
            "iron_ore",
            4260,
            74,
            160
        ]
    ],
    "bot1": {
        "location": [
            4264.23,
            75,
            156.15
        ],
        "rotation": [
            343.97,
            2.81
        ],
        "inventory": {
            "oak_planks": 3,
            "iron_ore": 4,
            "grass_block": 3,
            "bookshelf": 6
        }
    },
    "bot2": {
        "location": [
            4263.32,
            75,
            158.92
        ],
        "rotation": [
            172.37,
            -2.98
        ],
        "inventory": {
            "bookshelf": 4,
            "oak_planks": 2,
            "grass_block": 2
        }
    },
    "item_spots": {},
    "variants_config": {
        "agent_counts": [
            2
        ],
        "background": [
            "minecraft:oak_wood"
        ],
        "playground_location": {
            "name": "desert_villege",
            "x": [
                4259,
                4263
            ],
            "z": [
                159,
                163
            ],
            "y": 74,
            "bot_range": [
                [
                    4263,
                    4265
                ],
                [
                    155,
                    163
                ],
                75
            ],
            "center": [
                4261,
                74,
                161
            ]
        },
        "base_shape": [
            [
                3,
                1,
                2
            ]
        ],
        "block_type": [
            "grass_block",
            "bookshelf",
            "oak_planks",
            "bookshelf",
            "iron_ore"
        ],
        "placement_shape": [
            [
                2,
                1,
                0
            ],
            [
                1,
                1,
                0
            ],
            [
                2,
                0,
                0
            ],
            [
                1,
                0,
                0
            ],
            [
                0,
                0,
                0
            ]
        ],
        "block_count": 5,
        "placement_shape_number": [
            5,
            4,
            2,
            1,
            0
        ]
    },
    "bot_list": [
        "bot1",
        "bot2"
    ],
    "center_position": [
        4261,
        74,
        161
    ]
}