{
    "command": "\n                    await bot1.chat('hello!!!!!!!!!!!');\n                    await bot1.chat('/gamerule doMobSpawning false');\n                    await bot1.chat('/gamerule randomTickSpeed 0');\n                    \n                    await bot3.chat('/gamemode survival');\n                    await bot1.chat('/forceload add 220 131');\n                    await bot4.chat('/setblock 223 73 128 minecraft:barrier');\n                    await bot4.chat('/gamemode spectator');\n                    await bot4.chat('/tp @p 223 74 128 -90 90');\n                await bot1.chat('/fill 221 69 126 225 69 130 minecraft:stone');await bot1.chat('/fill 220 70 125 225 71 130 minecraft:air');await bot1.chat('/setblock 223 71 129 minecraft:dirt');await bot1.chat('/setblock 222 71 129 minecraft:sponge');await bot1.chat('/setblock 222 71 128 minecraft:clay');await bot1.chat('/setblock 222 71 127 minecraft:bookshelf');await bot1.chat('/setblock 223 70 129 minecraft:pumpkin');await bot1.chat('/setblock 222 70 129 minecraft:pumpkin');await bot1.chat('/setblock 223 70 128 minecraft:sponge');await bot1.chat('/setblock 222 70 128 minecraft:pumpkin');await bot1.chat('/setblock 223 70 127 minecraft:bricks');await bot1.chat('/setblock 222 70 127 minecraft:grass_block');await bot1.chat('/tp @p 227.81 72 125.21 148.6 5.4 ');await bot1.chat('/give @p pumpkin 2');await bot1.chat('/give @p grass_block 3');await bot1.chat('/give @p dirt 4');await bot1.chat('/give @p bookshelf 4');await bot1.chat('/give @p sponge 2');await bot1.chat('/give @p bricks 1');await bot1.chat('/give @p clay 2');await bot2.chat('/tp @p 226.58 72 130.71 306.3 9.36 ');await bot2.chat('/give @p pumpkin 6');await bot2.chat('/give @p bricks 4');await bot2.chat('/give @p sponge 3');await bot2.chat('/give @p clay 1');await bot2.chat('/give @p dirt 3');await bot2.chat('/give @p bookshelf 2');await bot3.chat('/tp @p 228.53 72 125.18 351.69 6.98 ');await bot3.chat('/give @p sponge 2');await bot3.chat('/give @p pumpkin 7');await bot3.chat('/give @p clay 5');await bot3.chat('/give @p dirt 3');await bot3.chat('/give @p bookshelf 3');await bot3.chat('/give @p bricks 1');",
    "obs_command": [
        [
            "\n                    await bot4.chat('/setblock 217 69 128 minecraft:barrier');\n                    await bot4.chat('/tp @p 217 70 128 -90 0');\n                "
        ],
        [
            "\n                    await bot4.chat('/setblock 223 69 134 minecraft:barrier');\n                    await bot4.chat('/tp @p 223 70 134 -180 0');\n                "
        ],
        [
            "\n                    await bot4.chat('/tp @p 223 74 128 -90 90');\n                "
        ],
        [
            "await bot1.chat('/fill 220 70 125 225 71 130 minecraft:air');"
        ]
    ],
    "variant": 100021,
    "actions": [
        [],
        [],
        [],
        []
    ],
    "done_input": [
        [
            "dirt",
            223,
            71,
            129
        ],
        [
            "sponge",
            222,
            71,
            129
        ],
        [
            "clay",
            222,
            71,
            128
        ],
        [
            "bookshelf",
            222,
            71,
            127
        ],
        [
            "pumpkin",
            223,
            70,
            129
        ],
        [
            "pumpkin",
            222,
            70,
            129
        ],
        [
            "sponge",
            223,
            70,
            128
        ],
        [
            "pumpkin",
            222,
            70,
            128
        ],
        [
            "bricks",
            223,
            70,
            127
        ],
        [
            "grass_block",
            222,
            70,
            127
        ]
    ],
    "bot1": {
        "location": [
            227.81,
            72,
            125.21
        ],
        "rotation": [
            148.6,
            5.4
        ],
        "inventory": {
            "pumpkin": 2,
            "grass_block": 3,
            "dirt": 4,
            "bookshelf": 4,
            "sponge": 2,
            "bricks": 1,
            "clay": 2
        }
    },
    "bot2": {
        "location": [
            226.58,
            72,
            130.71
        ],
        "rotation": [
            306.3,
            9.36
        ],
        "inventory": {
            "pumpkin": 6,
            "bricks": 4,
            "sponge": 3,
            "clay": 1,
            "dirt": 3,
            "bookshelf": 2
        }
    },
    "bot3": {
        "location": [
            228.53,
            72,
            125.18
        ],
        "rotation": [
            351.69,
            6.98
        ],
        "inventory": {
            "sponge": 2,
            "pumpkin": 7,
            "clay": 5,
            "dirt": 3,
            "bookshelf": 3,
            "bricks": 1
        }
    },
    "item_spots": {},
    "variants_config": {
        "agent_counts": [
            3
        ],
        "background": [
            "minecraft:stone"
        ],
        "playground_location": {
            "name": "villege",
            "x": [
                221,
                225
            ],
            "z": [
                126,
                130
            ],
            "y": 70,
            "bot_range": [
                [
                    226,
                    229
                ],
                [
                    125,
                    131
                ],
                72
            ],
            "center": [
                223,
                70,
                128
            ]
        },
        "base_shape": [
            [
                2,
                3,
                2
            ]
        ],
        "block_type": [
            "dirt",
            "sponge",
            "clay",
            "bookshelf",
            "pumpkin",
            "pumpkin",
            "sponge",
            "pumpkin",
            "bricks",
            "grass_block"
        ],
        "placement_shape": [
            [
                1,
                1,
                2
            ],
            [
                0,
                1,
                2
            ],
            [
                0,
                1,
                1
            ],
            [
                0,
                1,
                0
            ],
            [
                1,
                0,
                2
            ],
            [
                0,
                0,
                2
            ],
            [
                1,
                0,
                1
            ],
            [
                0,
                0,
                1
            ],
            [
                1,
                0,
                0
            ],
            [
                0,
                0,
                0
            ]
        ],
        "block_count": 10,
        "placement_shape_number": [
            11,
            10,
            8,
            6,
            5,
            4,
            3,
            2,
            1,
            0
        ]
    },
    "bot_list": [
        "bot1",
        "bot2",
        "bot3"
    ],
    "center_position": [
        223,
        70,
        128
    ]
}