{
    "command": "\n                    await bot1.chat('hello!!!!!!!!!!!');\n                    await bot1.chat('/gamerule doMobSpawning false');\n                    await bot1.chat('/gamerule randomTickSpeed 0');\n                    \n                    await bot3.chat('/gamemode spectator');\n                    await bot3.chat('/tp @p 10 10 10');\n                    await bot1.chat('/forceload add 4281 1129');\n                    await bot4.chat('/setblock 4284 67 1126 minecraft:barrier');\n                    await bot4.chat('/gamemode spectator');\n                    await bot4.chat('/tp @p 4284 68 1126 -90 90');\n                await bot1.chat('/fill 4282 63 1124 4286 63 1128 minecraft:glass');await bot1.chat('/fill 4281 64 1123 4286 65 1128 minecraft:air');await bot1.chat('/setblock 4283 65 1127 minecraft:oak_log');await bot1.chat('/setblock 4284 65 1126 minecraft:iron_ore');await bot1.chat('/setblock 4284 65 1125 minecraft:clay');await bot1.chat('/setblock 4283 64 1127 minecraft:bookshelf');await bot1.chat('/setblock 4284 64 1126 minecraft:coal_ore');await bot1.chat('/setblock 4283 64 1126 minecraft:bricks');await bot1.chat('/setblock 4284 64 1125 minecraft:stone');await bot1.chat('/setblock 4283 64 1125 minecraft:bookshelf');await bot1.chat('/tp @p 4285.98 65 1119.22 259.32 4.19 ');await bot1.chat('/give @p bookshelf 5');await bot1.chat('/give @p bricks 1');await bot1.chat('/give @p clay 6');await bot1.chat('/give @p oak_log 2');await bot2.chat('/tp @p 4284.12 65 1120.38 31.78 7.79 ');await bot2.chat('/give @p coal_ore 2');await bot2.chat('/give @p stone 1');await bot2.chat('/give @p oak_log 1');await bot2.chat('/give @p iron_ore 2');await bot2.chat('/give @p bricks 2');await bot2.chat('/give @p bookshelf 4');",
    "obs_command": [
        [
            "\n                    await bot4.chat('/setblock 4278 63 1126 minecraft:barrier');\n                    await bot4.chat('/tp @p 4278 64 1126 -90 0');\n                "
        ],
        [
            "\n                    await bot4.chat('/setblock 4284 63 1132 minecraft:barrier');\n                    await bot4.chat('/tp @p 4284 64 1132 -180 0');\n                "
        ],
        [
            "\n                    await bot4.chat('/tp @p 4284 68 1126 -90 90');\n                "
        ],
        [
            "await bot1.chat('/fill 4281 64 1123 4286 65 1128 minecraft:air');"
        ]
    ],
    "variant": 100038,
    "actions": [
        [],
        [],
        [],
        []
    ],
    "done_input": [
        [
            "oak_log",
            4283,
            65,
            1127
        ],
        [
            "iron_ore",
            4284,
            65,
            1126
        ],
        [
            "clay",
            4284,
            65,
            1125
        ],
        [
            "bookshelf",
            4283,
            64,
            1127
        ],
        [
            "coal_ore",
            4284,
            64,
            1126
        ],
        [
            "bricks",
            4283,
            64,
            1126
        ],
        [
            "stone",
            4284,
            64,
            1125
        ],
        [
            "bookshelf",
            4283,
            64,
            1125
        ]
    ],
    "bot1": {
        "location": [
            4285.98,
            65,
            1119.22
        ],
        "rotation": [
            259.32,
            4.19
        ],
        "inventory": {
            "bookshelf": 5,
            "bricks": 1,
            "clay": 6,
            "oak_log": 2
        }
    },
    "bot2": {
        "location": [
            4284.12,
            65,
            1120.38
        ],
        "rotation": [
            31.78,
            7.79
        ],
        "inventory": {
            "coal_ore": 2,
            "stone": 1,
            "oak_log": 1,
            "iron_ore": 2,
            "bricks": 2,
            "bookshelf": 4
        }
    },
    "item_spots": {},
    "variants_config": {
        "agent_counts": [
            2
        ],
        "background": [
            "minecraft:glass"
        ],
        "playground_location": {
            "name": "swamp",
            "x": [
                4282,
                4286
            ],
            "z": [
                1124,
                1128
            ],
            "y": 64,
            "bot_range": [
                [
                    4283,
                    4286
                ],
                [
                    1116,
                    1122
                ],
                65
            ],
            "center": [
                4284,
                64,
                1126
            ]
        },
        "base_shape": [
            [
                2,
                3,
                2
            ]
        ],
        "block_type": [
            "oak_log",
            "iron_ore",
            "clay",
            "bookshelf",
            "coal_ore",
            "bricks",
            "stone",
            "bookshelf"
        ],
        "placement_shape": [
            [
                0,
                1,
                2
            ],
            [
                1,
                1,
                1
            ],
            [
                1,
                1,
                0
            ],
            [
                0,
                0,
                2
            ],
            [
                1,
                0,
                1
            ],
            [
                0,
                0,
                1
            ],
            [
                1,
                0,
                0
            ],
            [
                0,
                0,
                0
            ]
        ],
        "block_count": 8,
        "placement_shape_number": [
            10,
            9,
            7,
            4,
            3,
            2,
            1,
            0
        ]
    },
    "bot_list": [
        "bot1",
        "bot2"
    ],
    "center_position": [
        4284,
        64,
        1126
    ]
}