{
    "command": "\n                    await bot1.chat('hello!!!!!!!!!!!');\n                    await bot1.chat('/gamerule doMobSpawning false');\n                    await bot1.chat('/gamerule randomTickSpeed 0');\n                    \n                    await bot3.chat('/gamemode survival');\n                    await bot1.chat('/forceload add 14137 10174');\n                    await bot4.chat('/setblock 14140 70 10171 minecraft:barrier');\n                    await bot4.chat('/gamemode spectator');\n                    await bot4.chat('/tp @p 14140 71 10171 -90 90');\n                await bot1.chat('/fill 14138 66 10169 14142 66 10173 minecraft:podzol');await bot1.chat('/fill 14137 67 10168 14142 68 10173 minecraft:air');await bot1.chat('/setblock 14141 68 10170 minecraft:bricks');await bot1.chat('/setblock 14140 68 10170 minecraft:oak_planks');await bot1.chat('/setblock 14139 68 10170 minecraft:sponge');await bot1.chat('/setblock 14141 67 10170 minecraft:bricks');await bot1.chat('/setblock 14140 67 10170 minecraft:pumpkin');await bot1.chat('/setblock 14139 67 10170 minecraft:clay');await bot1.chat('/tp @p 14145.9 69 10168.19 103.96 6.5 ');await bot1.chat('/give @p bricks 4');await bot1.chat('/give @p sponge 5');await bot1.chat('/give @p oak_planks 2');await bot1.chat('/give @p clay 1');await bot1.chat('/give @p pumpkin 3');await bot2.chat('/tp @p 14145.35 69 10173.34 193.53 6.19 ');await bot2.chat('/give @p pumpkin 1');await bot2.chat('/give @p oak_planks 2');await bot2.chat('/give @p sponge 2');await bot2.chat('/give @p clay 2');await bot3.chat('/tp @p 14145.68 69 10173.82 185.5 -0.94 ');await bot3.chat('/give @p clay 2');await bot3.chat('/give @p bricks 3');await bot3.chat('/give @p oak_planks 3');",
    "obs_command": [
        [
            "\n                    await bot4.chat('/setblock 14134 66 10171 minecraft:barrier');\n                    await bot4.chat('/tp @p 14134 67 10171 -90 0');\n                "
        ],
        [
            "\n                    await bot4.chat('/setblock 14140 66 10177 minecraft:barrier');\n                    await bot4.chat('/tp @p 14140 67 10177 -180 0');\n                "
        ],
        [
            "\n                    await bot4.chat('/tp @p 14140 71 10171 -90 90');\n                "
        ],
        [
            "await bot1.chat('/fill 14137 67 10168 14142 68 10173 minecraft:air');"
        ]
    ],
    "variant": 100001,
    "actions": [
        [],
        []
    ],
    "done_input": [
        [
            "bricks",
            14141,
            68,
            10170
        ],
        [
            "oak_planks",
            14140,
            68,
            10170
        ],
        [
            "sponge",
            14139,
            68,
            10170
        ],
        [
            "bricks",
            14141,
            67,
            10170
        ],
        [
            "pumpkin",
            14140,
            67,
            10170
        ],
        [
            "clay",
            14139,
            67,
            10170
        ]
    ],
    "bot1": {
        "location": [
            14145.9,
            69,
            10168.19
        ],
        "rotation": [
            103.96,
            6.5
        ],
        "inventory": {
            "bricks": 4,
            "sponge": 5,
            "oak_planks": 2,
            "clay": 1,
            "pumpkin": 3
        }
    },
    "bot2": {
        "location": [
            14145.35,
            69,
            10173.34
        ],
        "rotation": [
            193.53,
            6.19
        ],
        "inventory": {
            "pumpkin": 1,
            "oak_planks": 2,
            "sponge": 2,
            "clay": 2
        }
    },
    "bot3": {
        "location": [
            14145.68,
            69,
            10173.82
        ],
        "rotation": [
            185.5,
            -0.94
        ],
        "inventory": {
            "clay": 2,
            "bricks": 3,
            "oak_planks": 3
        }
    },
    "item_spots": {},
    "variants_config": {
        "agent_counts": [
            3
        ],
        "background": [
            "minecraft:podzol"
        ],
        "playground_location": {
            "name": "forest",
            "x": [
                14138,
                14142
            ],
            "z": [
                10169,
                10173
            ],
            "y": 67,
            "bot_range": [
                [
                    14145,
                    14148
                ],
                [
                    10168,
                    10174
                ],
                69
            ],
            "center": [
                14140,
                67,
                10171
            ]
        },
        "base_shape": [
            [
                3,
                1,
                2
            ]
        ],
        "block_type": [
            "bricks",
            "oak_planks",
            "sponge",
            "bricks",
            "pumpkin",
            "clay"
        ],
        "placement_shape": [
            [
                2,
                1,
                0
            ],
            [
                1,
                1,
                0
            ],
            [
                0,
                1,
                0
            ],
            [
                2,
                0,
                0
            ],
            [
                1,
                0,
                0
            ],
            [
                0,
                0,
                0
            ]
        ],
        "block_count": 6,
        "placement_shape_number": [
            5,
            4,
            3,
            2,
            1,
            0
        ]
    },
    "bot_list": [
        "bot1",
        "bot2",
        "bot3"
    ],
    "center_position": [
        14140,
        67,
        10171
    ]
}