{
    "command": "\n                    await bot1.chat('hello!!!!!!!!!!!');\n                    await bot1.chat('/gamerule doMobSpawning false');\n                    await bot1.chat('/gamerule randomTickSpeed 0');\n                    \n                    await bot3.chat('/gamemode survival');\n                    await bot1.chat('/forceload add 14137 10174');\n                    await bot4.chat('/setblock 14140 70 10171 minecraft:barrier');\n                    await bot4.chat('/gamemode spectator');\n                    await bot4.chat('/tp @p 14140 71 10171 -90 90');\n                await bot1.chat('/fill 14138 66 10169 14142 66 10173 minecraft:podzol');await bot1.chat('/fill 14137 67 10168 14142 68 10173 minecraft:air');await bot1.chat('/setblock 14140 68 10170 minecraft:clay');await bot1.chat('/setblock 14139 68 10170 minecraft:bricks');await bot1.chat('/setblock 14142 67 10170 minecraft:end_stone');await bot1.chat('/setblock 14141 67 10170 minecraft:end_stone');await bot1.chat('/setblock 14140 67 10170 minecraft:pumpkin');await bot1.chat('/setblock 14139 67 10170 minecraft:end_stone');await bot1.chat('/tp @p 14146.1 69 10171.01 217.68 2.28 ');await bot1.chat('/give @p end_stone 4');await bot1.chat('/give @p bricks 2');await bot1.chat('/give @p pumpkin 1');await bot2.chat('/tp @p 14147.71 69 10170.85 226.27 4.88 ');await bot2.chat('/give @p end_stone 6');await bot2.chat('/give @p clay 5');await bot2.chat('/give @p pumpkin 2');await bot3.chat('/tp @p 14147.04 69 10169.96 283.74 3.96 ');await bot3.chat('/give @p pumpkin 3');await bot3.chat('/give @p clay 3');await bot3.chat('/give @p end_stone 4');await bot3.chat('/give @p bricks 1');",
    "obs_command": [
        [
            "\n                    await bot4.chat('/setblock 14134 66 10171 minecraft:barrier');\n                    await bot4.chat('/tp @p 14134 67 10171 -90 0');\n                "
        ],
        [
            "\n                    await bot4.chat('/setblock 14140 66 10177 minecraft:barrier');\n                    await bot4.chat('/tp @p 14140 67 10177 -180 0');\n                "
        ],
        [
            "\n                    await bot4.chat('/tp @p 14140 71 10171 -90 90');\n                "
        ],
        [
            "await bot1.chat('/fill 14137 67 10168 14142 68 10173 minecraft:air');"
        ]
    ],
    "variant": 100003,
    "actions": [
        [],
        [],
        []
    ],
    "done_input": [
        [
            "clay",
            14140,
            68,
            10170
        ],
        [
            "bricks",
            14139,
            68,
            10170
        ],
        [
            "end_stone",
            14142,
            67,
            10170
        ],
        [
            "end_stone",
            14141,
            67,
            10170
        ],
        [
            "pumpkin",
            14140,
            67,
            10170
        ],
        [
            "end_stone",
            14139,
            67,
            10170
        ]
    ],
    "bot1": {
        "location": [
            14146.1,
            69,
            10171.01
        ],
        "rotation": [
            217.68,
            2.28
        ],
        "inventory": {
            "end_stone": 4,
            "bricks": 2,
            "pumpkin": 1
        }
    },
    "bot2": {
        "location": [
            14147.71,
            69,
            10170.85
        ],
        "rotation": [
            226.27,
            4.88
        ],
        "inventory": {
            "end_stone": 6,
            "clay": 5,
            "pumpkin": 2
        }
    },
    "bot3": {
        "location": [
            14147.04,
            69,
            10169.96
        ],
        "rotation": [
            283.74,
            3.96
        ],
        "inventory": {
            "pumpkin": 3,
            "clay": 3,
            "end_stone": 4,
            "bricks": 1
        }
    },
    "item_spots": {},
    "variants_config": {
        "agent_counts": [
            3
        ],
        "background": [
            "minecraft:podzol"
        ],
        "playground_location": {
            "name": "forest",
            "x": [
                14138,
                14142
            ],
            "z": [
                10169,
                10173
            ],
            "y": 67,
            "bot_range": [
                [
                    14145,
                    14148
                ],
                [
                    10168,
                    10174
                ],
                69
            ],
            "center": [
                14140,
                67,
                10171
            ]
        },
        "base_shape": [
            [
                4,
                1,
                2
            ]
        ],
        "block_type": [
            "clay",
            "bricks",
            "end_stone",
            "end_stone",
            "pumpkin",
            "end_stone"
        ],
        "placement_shape": [
            [
                1,
                1,
                0
            ],
            [
                0,
                1,
                0
            ],
            [
                3,
                0,
                0
            ],
            [
                2,
                0,
                0
            ],
            [
                1,
                0,
                0
            ],
            [
                0,
                0,
                0
            ]
        ],
        "block_count": 6,
        "placement_shape_number": [
            5,
            4,
            3,
            2,
            1,
            0
        ]
    },
    "bot_list": [
        "bot1",
        "bot2",
        "bot3"
    ],
    "center_position": [
        14140,
        67,
        10171
    ]
}