{
    "command": "\n                    await bot1.chat('hello!!!!!!!!!!!');\n                    await bot1.chat('/gamerule doMobSpawning false');\n                    await bot1.chat('/gamerule randomTickSpeed 0');\n                    \n                    await bot3.chat('/gamemode spectator');\n                    await bot3.chat('/tp @p 10 10 10');\n                    await bot1.chat('/forceload add 14137 10174');\n                    await bot4.chat('/setblock 14140 70 10171 minecraft:barrier');\n                    await bot4.chat('/gamemode spectator');\n                    await bot4.chat('/tp @p 14140 71 10171 -90 90');\n                await bot1.chat('/fill 14138 66 10169 14142 66 10173 minecraft:podzol');await bot1.chat('/fill 14137 67 10168 14142 68 10173 minecraft:air');await bot1.chat('/setblock 14141 68 10170 minecraft:purple_wool');await bot1.chat('/setblock 14140 68 10170 minecraft:emerald_block');await bot1.chat('/setblock 14139 68 10170 minecraft:birch_log');await bot1.chat('/setblock 14141 67 10170 minecraft:stone');await bot1.chat('/setblock 14140 67 10170 minecraft:sandstone');await bot1.chat('/setblock 14139 67 10170 minecraft:oak_fence');await bot1.chat('/tp @p 14146.24 69 10172.55 347.38 -1.89 ');await bot1.chat('/give @p stone 5');await bot1.chat('/give @p oak_fence 6');await bot1.chat('/give @p birch_log 4');await bot1.chat('/give @p sandstone 3');await bot1.chat('/give @p purple_wool 3');await bot2.chat('/tp @p 14147.38 69 10173.57 242.34 -7.34 ');await bot2.chat('/give @p sandstone 3');await bot2.chat('/give @p emerald_block 2');await bot2.chat('/give @p purple_wool 1');await bot2.chat('/give @p birch_log 3');",
    "obs_command": [
        [
            "\n                    await bot4.chat('/setblock 14134 66 10171 minecraft:barrier');\n                    await bot4.chat('/tp @p 14134 67 10171 -90 0');\n                "
        ],
        [
            "\n                    await bot4.chat('/setblock 14140 66 10177 minecraft:barrier');\n                    await bot4.chat('/tp @p 14140 67 10177 -180 0');\n                "
        ],
        [
            "\n                    await bot4.chat('/tp @p 14140 71 10171 -90 90');\n                "
        ],
        [
            "await bot1.chat('/fill 14137 67 10168 14142 68 10173 minecraft:air');"
        ]
    ],
    "variant": 100005,
    "actions": [
        [],
        [],
        []
    ],
    "done_input": [
        [
            "purple_wool",
            14141,
            68,
            10170
        ],
        [
            "emerald_block",
            14140,
            68,
            10170
        ],
        [
            "birch_log",
            14139,
            68,
            10170
        ],
        [
            "stone",
            14141,
            67,
            10170
        ],
        [
            "sandstone",
            14140,
            67,
            10170
        ],
        [
            "oak_fence",
            14139,
            67,
            10170
        ]
    ],
    "bot1": {
        "location": [
            14146.24,
            69,
            10172.55
        ],
        "rotation": [
            347.38,
            -1.89
        ],
        "inventory": {
            "stone": 5,
            "oak_fence": 6,
            "birch_log": 4,
            "sandstone": 3,
            "purple_wool": 3
        }
    },
    "bot2": {
        "location": [
            14147.38,
            69,
            10173.57
        ],
        "rotation": [
            242.34,
            -7.34
        ],
        "inventory": {
            "sandstone": 3,
            "emerald_block": 2,
            "purple_wool": 1,
            "birch_log": 3
        }
    },
    "item_spots": {},
    "variants_config": {
        "agent_counts": [
            2
        ],
        "background": [
            "minecraft:podzol"
        ],
        "playground_location": {
            "name": "forest",
            "x": [
                14138,
                14142
            ],
            "z": [
                10169,
                10173
            ],
            "y": 67,
            "bot_range": [
                [
                    14145,
                    14148
                ],
                [
                    10168,
                    10174
                ],
                69
            ],
            "center": [
                14140,
                67,
                10171
            ]
        },
        "base_shape": [
            [
                3,
                1,
                2
            ]
        ],
        "block_type": [
            "purple_wool",
            "emerald_block",
            "birch_log",
            "stone",
            "sandstone",
            "oak_fence"
        ],
        "placement_shape": [
            [
                2,
                1,
                0
            ],
            [
                1,
                1,
                0
            ],
            [
                0,
                1,
                0
            ],
            [
                2,
                0,
                0
            ],
            [
                1,
                0,
                0
            ],
            [
                0,
                0,
                0
            ]
        ],
        "block_count": 6,
        "placement_shape_number": [
            5,
            4,
            3,
            2,
            1,
            0
        ]
    },
    "bot_list": [
        "bot1",
        "bot2"
    ],
    "center_position": [
        14140,
        67,
        10171
    ]
}