{
    "command": "\n                    await bot1.chat('hello!!!!!!!!!!!');\n                    await bot1.chat('/gamerule doMobSpawning false');\n                    await bot1.chat('/gamerule randomTickSpeed 0');\n                    \n                    await bot3.chat('/gamemode spectator');\n                    await bot3.chat('/tp @p 10 10 10');\n                    await bot1.chat('/forceload add 14137 10174');\n                    await bot4.chat('/setblock 14140 70 10171 minecraft:barrier');\n                    await bot4.chat('/gamemode spectator');\n                    await bot4.chat('/tp @p 14140 71 10171 -90 90');\n                await bot1.chat('/fill 14138 66 10169 14142 66 10173 minecraft:podzol');await bot1.chat('/fill 14137 67 10168 14142 68 10173 minecraft:air');await bot1.chat('/setblock 14141 68 10170 minecraft:dirt');await bot1.chat('/setblock 14139 68 10170 minecraft:end_stone');await bot1.chat('/setblock 14142 67 10170 minecraft:pumpkin');await bot1.chat('/setblock 14141 67 10170 minecraft:sandstone');await bot1.chat('/setblock 14139 67 10170 minecraft:oak_fence');await bot1.chat('/tp @p 14147.26 69 10172.67 337.32 1.81 ');await bot1.chat('/give @p pumpkin 3');await bot1.chat('/give @p oak_fence 3');await bot1.chat('/give @p end_stone 1');await bot1.chat('/give @p sandstone 3');await bot2.chat('/tp @p 14146.5 69 10169.54 108.27 9.46 ');await bot2.chat('/give @p sandstone 3');await bot2.chat('/give @p dirt 5');await bot2.chat('/give @p pumpkin 1');await bot2.chat('/give @p end_stone 1');await bot2.chat('/give @p oak_fence 3');",
    "obs_command": [
        [
            "\n                    await bot4.chat('/setblock 14134 66 10171 minecraft:barrier');\n                    await bot4.chat('/tp @p 14134 67 10171 -90 0');\n                "
        ],
        [
            "\n                    await bot4.chat('/setblock 14140 66 10177 minecraft:barrier');\n                    await bot4.chat('/tp @p 14140 67 10177 -180 0');\n                "
        ],
        [
            "\n                    await bot4.chat('/tp @p 14140 71 10171 -90 90');\n                "
        ],
        [
            "await bot1.chat('/fill 14137 67 10168 14142 68 10173 minecraft:air');"
        ]
    ],
    "variant": 100008,
    "actions": [
        [],
        [],
        []
    ],
    "done_input": [
        [
            "dirt",
            14141,
            68,
            10170
        ],
        [
            "end_stone",
            14139,
            68,
            10170
        ],
        [
            "pumpkin",
            14142,
            67,
            10170
        ],
        [
            "sandstone",
            14141,
            67,
            10170
        ],
        [
            "oak_fence",
            14139,
            67,
            10170
        ]
    ],
    "bot1": {
        "location": [
            14147.26,
            69,
            10172.67
        ],
        "rotation": [
            337.32,
            1.81
        ],
        "inventory": {
            "pumpkin": 3,
            "oak_fence": 3,
            "end_stone": 1,
            "sandstone": 3
        }
    },
    "bot2": {
        "location": [
            14146.5,
            69,
            10169.54
        ],
        "rotation": [
            108.27,
            9.46
        ],
        "inventory": {
            "sandstone": 3,
            "dirt": 5,
            "pumpkin": 1,
            "end_stone": 1,
            "oak_fence": 3
        }
    },
    "item_spots": {},
    "variants_config": {
        "agent_counts": [
            2
        ],
        "background": [
            "minecraft:podzol"
        ],
        "playground_location": {
            "name": "forest",
            "x": [
                14138,
                14142
            ],
            "z": [
                10169,
                10173
            ],
            "y": 67,
            "bot_range": [
                [
                    14145,
                    14148
                ],
                [
                    10168,
                    10174
                ],
                69
            ],
            "center": [
                14140,
                67,
                10171
            ]
        },
        "base_shape": [
            [
                4,
                1,
                2
            ]
        ],
        "block_type": [
            "dirt",
            "end_stone",
            "pumpkin",
            "sandstone",
            "oak_fence"
        ],
        "placement_shape": [
            [
                2,
                1,
                0
            ],
            [
                0,
                1,
                0
            ],
            [
                3,
                0,
                0
            ],
            [
                2,
                0,
                0
            ],
            [
                0,
                0,
                0
            ]
        ],
        "block_count": 5,
        "placement_shape_number": [
            6,
            4,
            3,
            2,
            0
        ]
    },
    "bot_list": [
        "bot1",
        "bot2"
    ],
    "center_position": [
        14140,
        67,
        10171
    ]
}