{
    "command": "\n                    await bot1.chat('hello!!!!!!!!!!!');\n                    await bot1.chat('/gamerule doMobSpawning false');\n                    await bot1.chat('/gamerule randomTickSpeed 0');\n                    \n                    await bot3.chat('/gamemode spectator');\n                    await bot3.chat('/tp @p 10 10 10');\n                    await bot1.chat('/forceload add 14137 10174');\n                    await bot4.chat('/setblock 14140 70 10171 minecraft:barrier');\n                    await bot4.chat('/gamemode spectator');\n                    await bot4.chat('/tp @p 14140 71 10171 -90 90');\n                await bot1.chat('/fill 14138 66 10169 14142 66 10173 minecraft:podzol');await bot1.chat('/fill 14137 67 10168 14142 68 10173 minecraft:air');await bot1.chat('/setblock 14139 68 10171 minecraft:birch_log');await bot1.chat('/setblock 14140 67 10172 minecraft:gold_ore');await bot1.chat('/setblock 14139 67 10172 minecraft:dirt');await bot1.chat('/setblock 14140 67 10171 minecraft:iron_ore');await bot1.chat('/setblock 14139 67 10171 minecraft:gold_ore');await bot1.chat('/tp @p 14146.35 69 10170.46 329.54 3.04 ');await bot1.chat('/give @p gold_ore 4');await bot1.chat('/give @p birch_log 4');await bot1.chat('/give @p dirt 2');await bot2.chat('/tp @p 14145.83 69 10173.05 8.76 -9.82 ');await bot2.chat('/give @p dirt 4');await bot2.chat('/give @p iron_ore 5');await bot2.chat('/give @p birch_log 3');await bot2.chat('/give @p gold_ore 4');",
    "obs_command": [
        [
            "\n                    await bot4.chat('/setblock 14134 66 10171 minecraft:barrier');\n                    await bot4.chat('/tp @p 14134 67 10171 -90 0');\n                "
        ],
        [
            "\n                    await bot4.chat('/setblock 14140 66 10177 minecraft:barrier');\n                    await bot4.chat('/tp @p 14140 67 10177 -180 0');\n                "
        ],
        [
            "\n                    await bot4.chat('/tp @p 14140 71 10171 -90 90');\n                "
        ],
        [
            "await bot1.chat('/fill 14137 67 10168 14142 68 10173 minecraft:air');"
        ]
    ],
    "variant": 100009,
    "actions": [
        [],
        [],
        []
    ],
    "done_input": [
        [
            "birch_log",
            14139,
            68,
            10171
        ],
        [
            "gold_ore",
            14140,
            67,
            10172
        ],
        [
            "dirt",
            14139,
            67,
            10172
        ],
        [
            "iron_ore",
            14140,
            67,
            10171
        ],
        [
            "gold_ore",
            14139,
            67,
            10171
        ]
    ],
    "bot1": {
        "location": [
            14146.35,
            69,
            10170.46
        ],
        "rotation": [
            329.54,
            3.04
        ],
        "inventory": {
            "gold_ore": 4,
            "birch_log": 4,
            "dirt": 2
        }
    },
    "bot2": {
        "location": [
            14145.83,
            69,
            10173.05
        ],
        "rotation": [
            8.76,
            -9.82
        ],
        "inventory": {
            "dirt": 4,
            "iron_ore": 5,
            "birch_log": 3,
            "gold_ore": 4
        }
    },
    "item_spots": {},
    "variants_config": {
        "agent_counts": [
            2
        ],
        "background": [
            "minecraft:podzol"
        ],
        "playground_location": {
            "name": "forest",
            "x": [
                14138,
                14142
            ],
            "z": [
                10169,
                10173
            ],
            "y": 67,
            "bot_range": [
                [
                    14145,
                    14148
                ],
                [
                    10168,
                    10174
                ],
                69
            ],
            "center": [
                14140,
                67,
                10171
            ]
        },
        "base_shape": [
            [
                2,
                3,
                2
            ]
        ],
        "block_type": [
            "birch_log",
            "gold_ore",
            "dirt",
            "iron_ore",
            "gold_ore"
        ],
        "placement_shape": [
            [
                0,
                1,
                1
            ],
            [
                1,
                0,
                2
            ],
            [
                0,
                0,
                2
            ],
            [
                1,
                0,
                1
            ],
            [
                0,
                0,
                1
            ]
        ],
        "block_count": 5,
        "placement_shape_number": [
            8,
            5,
            4,
            3,
            2
        ]
    },
    "bot_list": [
        "bot1",
        "bot2"
    ],
    "center_position": [
        14140,
        67,
        10171
    ]
}