{
    "command": "\n                    await bot1.chat('hello!!!!!!!!!!!');\n                    await bot1.chat('/gamerule doMobSpawning false');\n                    await bot1.chat('/gamerule randomTickSpeed 0');\n                    \n                    await bot3.chat('/gamemode spectator');\n                    await bot3.chat('/tp @p 10 10 10');\n                    await bot1.chat('/forceload add 14137 10174');\n                    await bot4.chat('/setblock 14140 70 10171 minecraft:barrier');\n                    await bot4.chat('/gamemode spectator');\n                    await bot4.chat('/tp @p 14140 71 10171 -90 90');\n                await bot1.chat('/fill 14138 66 10169 14142 66 10173 minecraft:podzol');await bot1.chat('/fill 14137 67 10168 14142 68 10173 minecraft:air');await bot1.chat('/setblock 14139 68 10170 minecraft:coal_ore');await bot1.chat('/setblock 14142 67 10170 minecraft:dirt');await bot1.chat('/setblock 14141 67 10170 minecraft:pumpkin');await bot1.chat('/setblock 14140 67 10170 minecraft:emerald_block');await bot1.chat('/setblock 14139 67 10170 minecraft:orange_concrete');await bot1.chat('/tp @p 14147.01 69 10170.5 49.2 -3.13 ');await bot1.chat('/give @p dirt 4');await bot1.chat('/give @p orange_concrete 4');await bot1.chat('/give @p coal_ore 2');await bot2.chat('/tp @p 14146.32 69 10173.47 229.95 -4.1 ');await bot2.chat('/give @p pumpkin 2');await bot2.chat('/give @p emerald_block 1');await bot2.chat('/give @p orange_concrete 2');await bot2.chat('/give @p dirt 1');",
    "obs_command": [
        [
            "\n                    await bot4.chat('/setblock 14134 66 10171 minecraft:barrier');\n                    await bot4.chat('/tp @p 14134 67 10171 -90 0');\n                "
        ],
        [
            "\n                    await bot4.chat('/setblock 14140 66 10177 minecraft:barrier');\n                    await bot4.chat('/tp @p 14140 67 10177 -180 0');\n                "
        ],
        [
            "\n                    await bot4.chat('/tp @p 14140 71 10171 -90 90');\n                "
        ],
        [
            "await bot1.chat('/fill 14137 67 10168 14142 68 10173 minecraft:air');"
        ]
    ],
    "variant": 100011,
    "actions": [
        [],
        [],
        []
    ],
    "done_input": [
        [
            "coal_ore",
            14139,
            68,
            10170
        ],
        [
            "dirt",
            14142,
            67,
            10170
        ],
        [
            "pumpkin",
            14141,
            67,
            10170
        ],
        [
            "emerald_block",
            14140,
            67,
            10170
        ],
        [
            "orange_concrete",
            14139,
            67,
            10170
        ]
    ],
    "bot1": {
        "location": [
            14147.01,
            69,
            10170.5
        ],
        "rotation": [
            49.2,
            -3.13
        ],
        "inventory": {
            "dirt": 4,
            "orange_concrete": 4,
            "coal_ore": 2
        }
    },
    "bot2": {
        "location": [
            14146.32,
            69,
            10173.47
        ],
        "rotation": [
            229.95,
            -4.1
        ],
        "inventory": {
            "pumpkin": 2,
            "emerald_block": 1,
            "orange_concrete": 2,
            "dirt": 1
        }
    },
    "item_spots": {},
    "variants_config": {
        "agent_counts": [
            2
        ],
        "background": [
            "minecraft:podzol"
        ],
        "playground_location": {
            "name": "forest",
            "x": [
                14138,
                14142
            ],
            "z": [
                10169,
                10173
            ],
            "y": 67,
            "bot_range": [
                [
                    14145,
                    14148
                ],
                [
                    10168,
                    10174
                ],
                69
            ],
            "center": [
                14140,
                67,
                10171
            ]
        },
        "base_shape": [
            [
                4,
                1,
                2
            ]
        ],
        "block_type": [
            "coal_ore",
            "dirt",
            "pumpkin",
            "emerald_block",
            "orange_concrete"
        ],
        "placement_shape": [
            [
                0,
                1,
                0
            ],
            [
                3,
                0,
                0
            ],
            [
                2,
                0,
                0
            ],
            [
                1,
                0,
                0
            ],
            [
                0,
                0,
                0
            ]
        ],
        "block_count": 5,
        "placement_shape_number": [
            4,
            3,
            2,
            1,
            0
        ]
    },
    "bot_list": [
        "bot1",
        "bot2"
    ],
    "center_position": [
        14140,
        67,
        10171
    ]
}