{
    "command": "\n                    await bot1.chat('hello!!!!!!!!!!!');\n                    await bot1.chat('/gamerule doMobSpawning false');\n                    await bot1.chat('/gamerule randomTickSpeed 0');\n                    \n                    await bot3.chat('/gamemode spectator');\n                    await bot3.chat('/tp @p 10 10 10');\n                    await bot1.chat('/forceload add 14137 10174');\n                    await bot4.chat('/setblock 14140 70 10171 minecraft:barrier');\n                    await bot4.chat('/gamemode spectator');\n                    await bot4.chat('/tp @p 14140 71 10171 -90 90');\n                await bot1.chat('/fill 14138 66 10169 14142 66 10173 minecraft:podzol');await bot1.chat('/fill 14137 67 10168 14142 68 10173 minecraft:air');await bot1.chat('/setblock 14139 68 10171 minecraft:dirt');await bot1.chat('/setblock 14140 68 10170 minecraft:purple_wool');await bot1.chat('/setblock 14139 67 10171 minecraft:sandstone');await bot1.chat('/setblock 14140 67 10170 minecraft:birch_log');await bot1.chat('/setblock 14139 67 10170 minecraft:dirt');await bot1.chat('/tp @p 14147.35 69 10168.54 309.91 2.41 ');await bot1.chat('/give @p sandstone 3');await bot1.chat('/give @p dirt 4');await bot1.chat('/give @p birch_log 2');await bot2.chat('/tp @p 14147.75 69 10173.95 298.9 -9.78 ');await bot2.chat('/give @p birch_log 4');await bot2.chat('/give @p purple_wool 4');await bot2.chat('/give @p dirt 4');await bot2.chat('/give @p sandstone 1');",
    "obs_command": [
        [
            "\n                    await bot4.chat('/setblock 14134 66 10171 minecraft:barrier');\n                    await bot4.chat('/tp @p 14134 67 10171 -90 0');\n                "
        ],
        [
            "\n                    await bot4.chat('/setblock 14140 66 10177 minecraft:barrier');\n                    await bot4.chat('/tp @p 14140 67 10177 -180 0');\n                "
        ],
        [
            "\n                    await bot4.chat('/tp @p 14140 71 10171 -90 90');\n                "
        ],
        [
            "await bot1.chat('/fill 14137 67 10168 14142 68 10173 minecraft:air');"
        ]
    ],
    "variant": 100012,
    "actions": [
        [],
        [],
        []
    ],
    "done_input": [
        [
            "dirt",
            14139,
            68,
            10171
        ],
        [
            "purple_wool",
            14140,
            68,
            10170
        ],
        [
            "sandstone",
            14139,
            67,
            10171
        ],
        [
            "birch_log",
            14140,
            67,
            10170
        ],
        [
            "dirt",
            14139,
            67,
            10170
        ]
    ],
    "bot1": {
        "location": [
            14147.35,
            69,
            10168.54
        ],
        "rotation": [
            309.91,
            2.41
        ],
        "inventory": {
            "sandstone": 3,
            "dirt": 4,
            "birch_log": 2
        }
    },
    "bot2": {
        "location": [
            14147.75,
            69,
            10173.95
        ],
        "rotation": [
            298.9,
            -9.78
        ],
        "inventory": {
            "birch_log": 4,
            "purple_wool": 4,
            "dirt": 4,
            "sandstone": 1
        }
    },
    "item_spots": {},
    "variants_config": {
        "agent_counts": [
            2
        ],
        "background": [
            "minecraft:podzol"
        ],
        "playground_location": {
            "name": "forest",
            "x": [
                14138,
                14142
            ],
            "z": [
                10169,
                10173
            ],
            "y": 67,
            "bot_range": [
                [
                    14145,
                    14148
                ],
                [
                    10168,
                    10174
                ],
                69
            ],
            "center": [
                14140,
                67,
                10171
            ]
        },
        "base_shape": [
            [
                2,
                2,
                2
            ]
        ],
        "block_type": [
            "dirt",
            "purple_wool",
            "sandstone",
            "birch_log",
            "dirt"
        ],
        "placement_shape": [
            [
                0,
                1,
                1
            ],
            [
                1,
                1,
                0
            ],
            [
                0,
                0,
                1
            ],
            [
                1,
                0,
                0
            ],
            [
                0,
                0,
                0
            ]
        ],
        "block_count": 5,
        "placement_shape_number": [
            6,
            5,
            2,
            1,
            0
        ]
    },
    "bot_list": [
        "bot1",
        "bot2"
    ],
    "center_position": [
        14140,
        67,
        10171
    ]
}