{
    "command": "\n                    await bot1.chat('hello!!!!!!!!!!!');\n                    await bot1.chat('/gamerule doMobSpawning false');\n                    await bot1.chat('/gamerule randomTickSpeed 0');\n                    \n                    await bot3.chat('/gamemode spectator');\n                    await bot3.chat('/tp @p 10 10 10');\n                    await bot1.chat('/forceload add 14137 10174');\n                    await bot4.chat('/setblock 14140 70 10171 minecraft:barrier');\n                    await bot4.chat('/gamemode spectator');\n                    await bot4.chat('/tp @p 14140 71 10171 -90 90');\n                await bot1.chat('/fill 14138 66 10169 14142 66 10173 minecraft:podzol');await bot1.chat('/fill 14137 67 10168 14142 68 10173 minecraft:air');await bot1.chat('/setblock 14141 68 10170 minecraft:sea_lantern');await bot1.chat('/setblock 14140 68 10170 minecraft:sandstone');await bot1.chat('/setblock 14141 67 10170 minecraft:bricks');await bot1.chat('/setblock 14140 67 10170 minecraft:emerald_block');await bot1.chat('/setblock 14139 67 10170 minecraft:bricks');await bot1.chat('/tp @p 14147.11 69 10171.51 246.89 -4.78 ');await bot1.chat('/give @p bricks 7');await bot1.chat('/give @p sea_lantern 3');await bot1.chat('/give @p emerald_block 3');await bot2.chat('/tp @p 14145.72 69 10169.47 226.97 2.33 ');await bot2.chat('/give @p emerald_block 1');await bot2.chat('/give @p sandstone 3');await bot2.chat('/give @p bricks 2');await bot2.chat('/give @p sea_lantern 3');",
    "obs_command": [
        [
            "\n                    await bot4.chat('/setblock 14134 66 10171 minecraft:barrier');\n                    await bot4.chat('/tp @p 14134 67 10171 -90 0');\n                "
        ],
        [
            "\n                    await bot4.chat('/setblock 14140 66 10177 minecraft:barrier');\n                    await bot4.chat('/tp @p 14140 67 10177 -180 0');\n                "
        ],
        [
            "\n                    await bot4.chat('/tp @p 14140 71 10171 -90 90');\n                "
        ],
        [
            "await bot1.chat('/fill 14137 67 10168 14142 68 10173 minecraft:air');"
        ]
    ],
    "variant": 100013,
    "actions": [
        [],
        [],
        []
    ],
    "done_input": [
        [
            "sea_lantern",
            14141,
            68,
            10170
        ],
        [
            "sandstone",
            14140,
            68,
            10170
        ],
        [
            "bricks",
            14141,
            67,
            10170
        ],
        [
            "emerald_block",
            14140,
            67,
            10170
        ],
        [
            "bricks",
            14139,
            67,
            10170
        ]
    ],
    "bot1": {
        "location": [
            14147.11,
            69,
            10171.51
        ],
        "rotation": [
            246.89,
            -4.78
        ],
        "inventory": {
            "bricks": 7,
            "sea_lantern": 3,
            "emerald_block": 3
        }
    },
    "bot2": {
        "location": [
            14145.72,
            69,
            10169.47
        ],
        "rotation": [
            226.97,
            2.33
        ],
        "inventory": {
            "emerald_block": 1,
            "sandstone": 3,
            "bricks": 2,
            "sea_lantern": 3
        }
    },
    "item_spots": {},
    "variants_config": {
        "agent_counts": [
            2
        ],
        "background": [
            "minecraft:podzol"
        ],
        "playground_location": {
            "name": "forest",
            "x": [
                14138,
                14142
            ],
            "z": [
                10169,
                10173
            ],
            "y": 67,
            "bot_range": [
                [
                    14145,
                    14148
                ],
                [
                    10168,
                    10174
                ],
                69
            ],
            "center": [
                14140,
                67,
                10171
            ]
        },
        "base_shape": [
            [
                3,
                1,
                2
            ]
        ],
        "block_type": [
            "sea_lantern",
            "sandstone",
            "bricks",
            "emerald_block",
            "bricks"
        ],
        "placement_shape": [
            [
                2,
                1,
                0
            ],
            [
                1,
                1,
                0
            ],
            [
                2,
                0,
                0
            ],
            [
                1,
                0,
                0
            ],
            [
                0,
                0,
                0
            ]
        ],
        "block_count": 5,
        "placement_shape_number": [
            5,
            4,
            2,
            1,
            0
        ]
    },
    "bot_list": [
        "bot1",
        "bot2"
    ],
    "center_position": [
        14140,
        67,
        10171
    ]
}