{
    "command": "\n                    await bot1.chat('hello!!!!!!!!!!!');\n                    await bot1.chat('/gamerule doMobSpawning false');\n                    await bot1.chat('/gamerule randomTickSpeed 0');\n                    \n                    await bot3.chat('/gamemode spectator');\n                    await bot3.chat('/tp @p 10 10 10');\n                    await bot1.chat('/forceload add 14137 10174');\n                    await bot4.chat('/setblock 14140 70 10171 minecraft:barrier');\n                    await bot4.chat('/gamemode spectator');\n                    await bot4.chat('/tp @p 14140 71 10171 -90 90');\n                await bot1.chat('/fill 14138 66 10169 14142 66 10173 minecraft:podzol');await bot1.chat('/fill 14137 67 10168 14142 68 10173 minecraft:air');await bot1.chat('/setblock 14140 68 10170 minecraft:bricks');await bot1.chat('/setblock 14140 67 10172 minecraft:bricks');await bot1.chat('/setblock 14139 67 10172 minecraft:coal_ore');await bot1.chat('/setblock 14140 67 10171 minecraft:end_stone');await bot1.chat('/setblock 14139 67 10171 minecraft:gold_ore');await bot1.chat('/setblock 14140 67 10170 minecraft:oak_fence');await bot1.chat('/setblock 14139 67 10170 minecraft:sandstone');await bot1.chat('/tp @p 14147.97 69 10168.42 66.63 8.96 ');await bot1.chat('/give @p bricks 10');await bot1.chat('/give @p sandstone 4');await bot1.chat('/give @p end_stone 2');await bot1.chat('/give @p coal_ore 3');await bot2.chat('/tp @p 14147.18 69 10170.58 208.24 -6.47 ');await bot2.chat('/give @p coal_ore 2');await bot2.chat('/give @p oak_fence 2');await bot2.chat('/give @p gold_ore 5');await bot2.chat('/give @p bricks 1');",
    "obs_command": [
        [
            "\n                    await bot4.chat('/setblock 14134 66 10171 minecraft:barrier');\n                    await bot4.chat('/tp @p 14134 67 10171 -90 0');\n                "
        ],
        [
            "\n                    await bot4.chat('/setblock 14140 66 10177 minecraft:barrier');\n                    await bot4.chat('/tp @p 14140 67 10177 -180 0');\n                "
        ],
        [
            "\n                    await bot4.chat('/tp @p 14140 71 10171 -90 90');\n                "
        ],
        [
            "await bot1.chat('/fill 14137 67 10168 14142 68 10173 minecraft:air');"
        ]
    ],
    "variant": 100014,
    "actions": [
        [],
        [],
        [],
        []
    ],
    "done_input": [
        [
            "bricks",
            14140,
            68,
            10170
        ],
        [
            "bricks",
            14140,
            67,
            10172
        ],
        [
            "coal_ore",
            14139,
            67,
            10172
        ],
        [
            "end_stone",
            14140,
            67,
            10171
        ],
        [
            "gold_ore",
            14139,
            67,
            10171
        ],
        [
            "oak_fence",
            14140,
            67,
            10170
        ],
        [
            "sandstone",
            14139,
            67,
            10170
        ]
    ],
    "bot1": {
        "location": [
            14147.97,
            69,
            10168.42
        ],
        "rotation": [
            66.63,
            8.96
        ],
        "inventory": {
            "bricks": 10,
            "sandstone": 4,
            "end_stone": 2,
            "coal_ore": 3
        }
    },
    "bot2": {
        "location": [
            14147.18,
            69,
            10170.58
        ],
        "rotation": [
            208.24,
            -6.47
        ],
        "inventory": {
            "coal_ore": 2,
            "oak_fence": 2,
            "gold_ore": 5,
            "bricks": 1
        }
    },
    "item_spots": {},
    "variants_config": {
        "agent_counts": [
            2
        ],
        "background": [
            "minecraft:podzol"
        ],
        "playground_location": {
            "name": "forest",
            "x": [
                14138,
                14142
            ],
            "z": [
                10169,
                10173
            ],
            "y": 67,
            "bot_range": [
                [
                    14145,
                    14148
                ],
                [
                    10168,
                    10174
                ],
                69
            ],
            "center": [
                14140,
                67,
                10171
            ]
        },
        "base_shape": [
            [
                2,
                3,
                2
            ]
        ],
        "block_type": [
            "bricks",
            "bricks",
            "coal_ore",
            "end_stone",
            "gold_ore",
            "oak_fence",
            "sandstone"
        ],
        "placement_shape": [
            [
                1,
                1,
                0
            ],
            [
                1,
                0,
                2
            ],
            [
                0,
                0,
                2
            ],
            [
                1,
                0,
                1
            ],
            [
                0,
                0,
                1
            ],
            [
                1,
                0,
                0
            ],
            [
                0,
                0,
                0
            ]
        ],
        "block_count": 7,
        "placement_shape_number": [
            7,
            5,
            4,
            3,
            2,
            1,
            0
        ]
    },
    "bot_list": [
        "bot1",
        "bot2"
    ],
    "center_position": [
        14140,
        67,
        10171
    ]
}