{
    "command": "\n                    await bot1.chat('hello!!!!!!!!!!!');\n                    await bot1.chat('/gamerule doMobSpawning false');\n                    await bot1.chat('/gamerule randomTickSpeed 0');\n                    \n                    await bot3.chat('/gamemode survival');\n                    await bot1.chat('/forceload add 14137 10174');\n                    await bot4.chat('/setblock 14140 70 10171 minecraft:barrier');\n                    await bot4.chat('/gamemode spectator');\n                    await bot4.chat('/tp @p 14140 71 10171 -90 90');\n                await bot1.chat('/fill 14138 66 10169 14142 66 10173 minecraft:podzol');await bot1.chat('/fill 14137 67 10168 14142 68 10173 minecraft:air');await bot1.chat('/setblock 14140 68 10171 minecraft:clay');await bot1.chat('/setblock 14139 68 10171 minecraft:sponge');await bot1.chat('/setblock 14139 68 10170 minecraft:stone');await bot1.chat('/setblock 14140 67 10171 minecraft:stone');await bot1.chat('/setblock 14139 67 10171 minecraft:sea_lantern');await bot1.chat('/setblock 14140 67 10170 minecraft:oak_planks');await bot1.chat('/setblock 14139 67 10170 minecraft:oak_planks');await bot1.chat('/tp @p 14145.19 69 10169.27 236.21 5.16 ');await bot1.chat('/give @p stone 6');await bot1.chat('/give @p oak_planks 6');await bot1.chat('/give @p sea_lantern 3');await bot1.chat('/give @p sponge 2');await bot2.chat('/tp @p 14147.55 69 10172.17 198.95 -3.59 ');await bot2.chat('/give @p sea_lantern 3');await bot2.chat('/give @p sponge 2');await bot2.chat('/give @p oak_planks 1');await bot2.chat('/give @p stone 3');await bot3.chat('/tp @p 14146.91 69 10168.05 120.83 5.14 ');await bot3.chat('/give @p oak_planks 2');await bot3.chat('/give @p clay 5');",
    "obs_command": [
        [
            "\n                    await bot4.chat('/setblock 14134 66 10171 minecraft:barrier');\n                    await bot4.chat('/tp @p 14134 67 10171 -90 0');\n                "
        ],
        [
            "\n                    await bot4.chat('/setblock 14140 66 10177 minecraft:barrier');\n                    await bot4.chat('/tp @p 14140 67 10177 -180 0');\n                "
        ],
        [
            "\n                    await bot4.chat('/tp @p 14140 71 10171 -90 90');\n                "
        ],
        [
            "await bot1.chat('/fill 14137 67 10168 14142 68 10173 minecraft:air');"
        ]
    ],
    "variant": 100019,
    "actions": [
        [],
        [],
        []
    ],
    "done_input": [
        [
            "clay",
            14140,
            68,
            10171
        ],
        [
            "sponge",
            14139,
            68,
            10171
        ],
        [
            "stone",
            14139,
            68,
            10170
        ],
        [
            "stone",
            14140,
            67,
            10171
        ],
        [
            "sea_lantern",
            14139,
            67,
            10171
        ],
        [
            "oak_planks",
            14140,
            67,
            10170
        ],
        [
            "oak_planks",
            14139,
            67,
            10170
        ]
    ],
    "bot1": {
        "location": [
            14145.19,
            69,
            10169.27
        ],
        "rotation": [
            236.21,
            5.16
        ],
        "inventory": {
            "stone": 6,
            "oak_planks": 6,
            "sea_lantern": 3,
            "sponge": 2
        }
    },
    "bot2": {
        "location": [
            14147.55,
            69,
            10172.17
        ],
        "rotation": [
            198.95,
            -3.59
        ],
        "inventory": {
            "sea_lantern": 3,
            "sponge": 2,
            "oak_planks": 1,
            "stone": 3
        }
    },
    "bot3": {
        "location": [
            14146.91,
            69,
            10168.05
        ],
        "rotation": [
            120.83,
            5.14
        ],
        "inventory": {
            "oak_planks": 2,
            "clay": 5
        }
    },
    "item_spots": {},
    "variants_config": {
        "agent_counts": [
            3
        ],
        "background": [
            "minecraft:podzol"
        ],
        "playground_location": {
            "name": "forest",
            "x": [
                14138,
                14142
            ],
            "z": [
                10169,
                10173
            ],
            "y": 67,
            "bot_range": [
                [
                    14145,
                    14148
                ],
                [
                    10168,
                    10174
                ],
                69
            ],
            "center": [
                14140,
                67,
                10171
            ]
        },
        "base_shape": [
            [
                2,
                2,
                2
            ]
        ],
        "block_type": [
            "clay",
            "sponge",
            "stone",
            "stone",
            "sea_lantern",
            "oak_planks",
            "oak_planks"
        ],
        "placement_shape": [
            [
                1,
                1,
                1
            ],
            [
                0,
                1,
                1
            ],
            [
                0,
                1,
                0
            ],
            [
                1,
                0,
                1
            ],
            [
                0,
                0,
                1
            ],
            [
                1,
                0,
                0
            ],
            [
                0,
                0,
                0
            ]
        ],
        "block_count": 7,
        "placement_shape_number": [
            7,
            6,
            4,
            3,
            2,
            1,
            0
        ]
    },
    "bot_list": [
        "bot1",
        "bot2",
        "bot3"
    ],
    "center_position": [
        14140,
        67,
        10171
    ]
}