{
    "command": "\n                    await bot1.chat('hello!!!!!!!!!!!');\n                    await bot1.chat('/gamerule doMobSpawning false');\n                    await bot1.chat('/gamerule randomTickSpeed 0');\n                    \n                    await bot3.chat('/gamemode spectator');\n                    await bot3.chat('/tp @p 10 10 10');\n                    await bot1.chat('/forceload add 4258 164');\n                    await bot4.chat('/setblock 4261 77 161 minecraft:barrier');\n                    await bot4.chat('/gamemode spectator');\n                    await bot4.chat('/tp @p 4261 78 161 -90 90');\n                await bot1.chat('/fill 4259 73 159 4263 73 163 minecraft:oak_wood');await bot1.chat('/fill 4258 74 158 4263 75 163 minecraft:air');await bot1.chat('/setblock 4261 75 161 minecraft:sandstone');await bot1.chat('/setblock 4261 74 161 minecraft:dirt');await bot1.chat('/setblock 4260 74 161 minecraft:birch_log');await bot1.chat('/setblock 4261 74 160 minecraft:orange_concrete');await bot1.chat('/setblock 4260 74 160 minecraft:pumpkin');await bot1.chat('/tp @p 4263.62 75 158.01 321.34 8.32 ');await bot1.chat('/give @p dirt 5');await bot1.chat('/give @p pumpkin 1');await bot1.chat('/give @p sandstone 1');await bot1.chat('/give @p birch_log 1');await bot2.chat('/tp @p 4263.76 75 155.94 147.67 3.54 ');await bot2.chat('/give @p birch_log 2');await bot2.chat('/give @p orange_concrete 6');await bot2.chat('/give @p pumpkin 2');await bot2.chat('/give @p sandstone 1');",
    "obs_command": [
        [
            "\n                    await bot4.chat('/setblock 4255 73 161 minecraft:barrier');\n                    await bot4.chat('/tp @p 4255 74 161 -90 0');\n                "
        ],
        [
            "\n                    await bot4.chat('/setblock 4261 73 167 minecraft:barrier');\n                    await bot4.chat('/tp @p 4261 74 167 -180 0');\n                "
        ],
        [
            "\n                    await bot4.chat('/tp @p 4261 78 161 -90 90');\n                "
        ],
        [
            "await bot1.chat('/fill 4258 74 158 4263 75 163 minecraft:air');"
        ]
    ],
    "variant": 100017,
    "actions": [
        [],
        [],
        []
    ],
    "done_input": [
        [
            "sandstone",
            4261,
            75,
            161
        ],
        [
            "dirt",
            4261,
            74,
            161
        ],
        [
            "birch_log",
            4260,
            74,
            161
        ],
        [
            "orange_concrete",
            4261,
            74,
            160
        ],
        [
            "pumpkin",
            4260,
            74,
            160
        ]
    ],
    "bot1": {
        "location": [
            4263.62,
            75,
            158.01
        ],
        "rotation": [
            321.34,
            8.32
        ],
        "inventory": {
            "dirt": 5,
            "pumpkin": 1,
            "sandstone": 1,
            "birch_log": 1
        }
    },
    "bot2": {
        "location": [
            4263.76,
            75,
            155.94
        ],
        "rotation": [
            147.67,
            3.54
        ],
        "inventory": {
            "birch_log": 2,
            "orange_concrete": 6,
            "pumpkin": 2,
            "sandstone": 1
        }
    },
    "item_spots": {},
    "variants_config": {
        "agent_counts": [
            2
        ],
        "background": [
            "minecraft:oak_wood"
        ],
        "playground_location": {
            "name": "desert_villege",
            "x": [
                4259,
                4263
            ],
            "z": [
                159,
                163
            ],
            "y": 74,
            "bot_range": [
                [
                    4263,
                    4265
                ],
                [
                    155,
                    163
                ],
                75
            ],
            "center": [
                4261,
                74,
                161
            ]
        },
        "base_shape": [
            [
                2,
                2,
                2
            ]
        ],
        "block_type": [
            "sandstone",
            "dirt",
            "birch_log",
            "orange_concrete",
            "pumpkin"
        ],
        "placement_shape": [
            [
                1,
                1,
                1
            ],
            [
                1,
                0,
                1
            ],
            [
                0,
                0,
                1
            ],
            [
                1,
                0,
                0
            ],
            [
                0,
                0,
                0
            ]
        ],
        "block_count": 5,
        "placement_shape_number": [
            7,
            3,
            2,
            1,
            0
        ]
    },
    "bot_list": [
        "bot1",
        "bot2"
    ],
    "center_position": [
        4261,
        74,
        161
    ]
}