{
    "command": "\n                    await bot1.chat('hello!!!!!!!!!!!');\n                    await bot1.chat('/gamerule doMobSpawning false');\n                    await bot1.chat('/gamerule randomTickSpeed 0');\n                    \n                    await bot3.chat('/gamemode spectator');\n                    await bot3.chat('/tp @p 10 10 10');\n                    await bot1.chat('/forceload add 14137 10174');\n                    await bot4.chat('/setblock 14140 70 10171 minecraft:barrier');\n                    await bot4.chat('/gamemode spectator');\n                    await bot4.chat('/tp @p 14140 71 10171 -90 90');\n                await bot1.chat('/fill 14138 66 10169 14142 66 10173 minecraft:podzol');await bot1.chat('/fill 14137 67 10168 14142 68 10173 minecraft:air');await bot1.chat('/setblock 14140 68 10172 minecraft:dirt');await bot1.chat('/setblock 14139 68 10172 minecraft:sponge');await bot1.chat('/setblock 14139 68 10171 minecraft:dirt');await bot1.chat('/setblock 14140 67 10172 minecraft:dirt');await bot1.chat('/setblock 14139 67 10172 minecraft:sponge');await bot1.chat('/setblock 14140 67 10171 minecraft:emerald_block');await bot1.chat('/setblock 14139 67 10171 minecraft:sea_lantern');await bot1.chat('/setblock 14140 67 10170 minecraft:pumpkin');await bot1.chat('/setblock 14139 67 10170 minecraft:pumpkin');await bot1.chat('/tp @p 14147.81 69 10170.37 32.86 4.65 ');await bot1.chat('/give @p dirt 11');await bot1.chat('/give @p pumpkin 1');await bot1.chat('/give @p emerald_block 2');await bot1.chat('/give @p sponge 3');await bot2.chat('/tp @p 14145.56 69 10172.84 163.59 3.57 ');await bot2.chat('/give @p sponge 6');await bot2.chat('/give @p pumpkin 5');await bot2.chat('/give @p sea_lantern 4');await bot2.chat('/give @p dirt 6');await bot2.chat('/give @p emerald_block 1');",
    "obs_command": [
        [
            "\n                    await bot4.chat('/setblock 14134 66 10171 minecraft:barrier');\n                    await bot4.chat('/tp @p 14134 67 10171 -90 0');\n                "
        ],
        [
            "\n                    await bot4.chat('/setblock 14140 66 10177 minecraft:barrier');\n                    await bot4.chat('/tp @p 14140 67 10177 -180 0');\n                "
        ],
        [
            "\n                    await bot4.chat('/tp @p 14140 71 10171 -90 90');\n                "
        ],
        [
            "await bot1.chat('/fill 14137 67 10168 14142 68 10173 minecraft:air');"
        ]
    ],
    "variant": 100028,
    "actions": [
        [],
        [],
        [],
        [],
        []
    ],
    "done_input": [
        [
            "dirt",
            14140,
            68,
            10172
        ],
        [
            "sponge",
            14139,
            68,
            10172
        ],
        [
            "dirt",
            14139,
            68,
            10171
        ],
        [
            "dirt",
            14140,
            67,
            10172
        ],
        [
            "sponge",
            14139,
            67,
            10172
        ],
        [
            "emerald_block",
            14140,
            67,
            10171
        ],
        [
            "sea_lantern",
            14139,
            67,
            10171
        ],
        [
            "pumpkin",
            14140,
            67,
            10170
        ],
        [
            "pumpkin",
            14139,
            67,
            10170
        ]
    ],
    "bot1": {
        "location": [
            14147.81,
            69,
            10170.37
        ],
        "rotation": [
            32.86,
            4.65
        ],
        "inventory": {
            "dirt": 11,
            "pumpkin": 1,
            "emerald_block": 2,
            "sponge": 3
        }
    },
    "bot2": {
        "location": [
            14145.56,
            69,
            10172.84
        ],
        "rotation": [
            163.59,
            3.57
        ],
        "inventory": {
            "sponge": 6,
            "pumpkin": 5,
            "sea_lantern": 4,
            "dirt": 6,
            "emerald_block": 1
        }
    },
    "item_spots": {},
    "variants_config": {
        "agent_counts": [
            2
        ],
        "background": [
            "minecraft:podzol"
        ],
        "playground_location": {
            "name": "forest",
            "x": [
                14138,
                14142
            ],
            "z": [
                10169,
                10173
            ],
            "y": 67,
            "bot_range": [
                [
                    14145,
                    14148
                ],
                [
                    10168,
                    10174
                ],
                69
            ],
            "center": [
                14140,
                67,
                10171
            ]
        },
        "base_shape": [
            [
                2,
                3,
                2
            ]
        ],
        "block_type": [
            "dirt",
            "sponge",
            "dirt",
            "dirt",
            "sponge",
            "emerald_block",
            "sea_lantern",
            "pumpkin",
            "pumpkin"
        ],
        "placement_shape": [
            [
                1,
                1,
                2
            ],
            [
                0,
                1,
                2
            ],
            [
                0,
                1,
                1
            ],
            [
                1,
                0,
                2
            ],
            [
                0,
                0,
                2
            ],
            [
                1,
                0,
                1
            ],
            [
                0,
                0,
                1
            ],
            [
                1,
                0,
                0
            ],
            [
                0,
                0,
                0
            ]
        ],
        "block_count": 9,
        "placement_shape_number": [
            11,
            10,
            8,
            5,
            4,
            3,
            2,
            1,
            0
        ]
    },
    "bot_list": [
        "bot1",
        "bot2"
    ],
    "center_position": [
        14140,
        67,
        10171
    ]
}