{
    "command": "\n                    await bot1.chat('hello!!!!!!!!!!!');\n                    await bot1.chat('/gamerule doMobSpawning false');\n                    await bot1.chat('/gamerule randomTickSpeed 0');\n                    \n                    await bot3.chat('/gamemode spectator');\n                    await bot3.chat('/tp @p 10 10 10');\n                    await bot1.chat('/forceload add 14137 10174');\n                    await bot4.chat('/setblock 14140 70 10171 minecraft:barrier');\n                    await bot4.chat('/gamemode spectator');\n                    await bot4.chat('/tp @p 14140 71 10171 -90 90');\n                await bot1.chat('/fill 14138 66 10169 14142 66 10173 minecraft:podzol');await bot1.chat('/fill 14137 67 10168 14142 68 10173 minecraft:air');await bot1.chat('/setblock 14140 68 10172 minecraft:stone');await bot1.chat('/setblock 14140 68 10171 minecraft:purple_wool');await bot1.chat('/setblock 14140 68 10170 minecraft:sponge');await bot1.chat('/setblock 14139 68 10170 minecraft:dirt');await bot1.chat('/setblock 14140 67 10172 minecraft:bricks');await bot1.chat('/setblock 14140 67 10171 minecraft:purple_wool');await bot1.chat('/setblock 14139 67 10171 minecraft:orange_concrete');await bot1.chat('/setblock 14140 67 10170 minecraft:iron_ore');await bot1.chat('/setblock 14139 67 10170 minecraft:sandstone');await bot1.chat('/tp @p 14146.12 69 10168.02 335.09 0.6 ');await bot1.chat('/give @p bricks 5');await bot1.chat('/give @p sandstone 1');await bot1.chat('/give @p orange_concrete 1');await bot1.chat('/give @p dirt 5');await bot1.chat('/give @p purple_wool 3');await bot1.chat('/give @p stone 2');await bot2.chat('/tp @p 14145.64 69 10169.94 69.21 -7.56 ');await bot2.chat('/give @p purple_wool 3');await bot2.chat('/give @p iron_ore 3');await bot2.chat('/give @p stone 1');await bot2.chat('/give @p sponge 3');await bot2.chat('/give @p bricks 1');await bot2.chat('/give @p orange_concrete 2');",
    "obs_command": [
        [
            "\n                    await bot4.chat('/setblock 14134 66 10171 minecraft:barrier');\n                    await bot4.chat('/tp @p 14134 67 10171 -90 0');\n                "
        ],
        [
            "\n                    await bot4.chat('/setblock 14140 66 10177 minecraft:barrier');\n                    await bot4.chat('/tp @p 14140 67 10177 -180 0');\n                "
        ],
        [
            "\n                    await bot4.chat('/tp @p 14140 71 10171 -90 90');\n                "
        ],
        [
            "await bot1.chat('/fill 14137 67 10168 14142 68 10173 minecraft:air');"
        ]
    ],
    "variant": 100033,
    "actions": [
        [],
        [],
        [],
        [],
        []
    ],
    "done_input": [
        [
            "stone",
            14140,
            68,
            10172
        ],
        [
            "purple_wool",
            14140,
            68,
            10171
        ],
        [
            "sponge",
            14140,
            68,
            10170
        ],
        [
            "dirt",
            14139,
            68,
            10170
        ],
        [
            "bricks",
            14140,
            67,
            10172
        ],
        [
            "purple_wool",
            14140,
            67,
            10171
        ],
        [
            "orange_concrete",
            14139,
            67,
            10171
        ],
        [
            "iron_ore",
            14140,
            67,
            10170
        ],
        [
            "sandstone",
            14139,
            67,
            10170
        ]
    ],
    "bot1": {
        "location": [
            14146.12,
            69,
            10168.02
        ],
        "rotation": [
            335.09,
            0.6
        ],
        "inventory": {
            "bricks": 5,
            "sandstone": 1,
            "orange_concrete": 1,
            "dirt": 5,
            "purple_wool": 3,
            "stone": 2
        }
    },
    "bot2": {
        "location": [
            14145.64,
            69,
            10169.94
        ],
        "rotation": [
            69.21,
            -7.56
        ],
        "inventory": {
            "purple_wool": 3,
            "iron_ore": 3,
            "stone": 1,
            "sponge": 3,
            "bricks": 1,
            "orange_concrete": 2
        }
    },
    "item_spots": {},
    "variants_config": {
        "agent_counts": [
            2
        ],
        "background": [
            "minecraft:podzol"
        ],
        "playground_location": {
            "name": "forest",
            "x": [
                14138,
                14142
            ],
            "z": [
                10169,
                10173
            ],
            "y": 67,
            "bot_range": [
                [
                    14145,
                    14148
                ],
                [
                    10168,
                    10174
                ],
                69
            ],
            "center": [
                14140,
                67,
                10171
            ]
        },
        "base_shape": [
            [
                2,
                3,
                2
            ]
        ],
        "block_type": [
            "stone",
            "purple_wool",
            "sponge",
            "dirt",
            "bricks",
            "purple_wool",
            "orange_concrete",
            "iron_ore",
            "sandstone"
        ],
        "placement_shape": [
            [
                1,
                1,
                2
            ],
            [
                1,
                1,
                1
            ],
            [
                1,
                1,
                0
            ],
            [
                0,
                1,
                0
            ],
            [
                1,
                0,
                2
            ],
            [
                1,
                0,
                1
            ],
            [
                0,
                0,
                1
            ],
            [
                1,
                0,
                0
            ],
            [
                0,
                0,
                0
            ]
        ],
        "block_count": 9,
        "placement_shape_number": [
            11,
            9,
            7,
            6,
            5,
            3,
            2,
            1,
            0
        ]
    },
    "bot_list": [
        "bot1",
        "bot2"
    ],
    "center_position": [
        14140,
        67,
        10171
    ]
}