{
    "command": "\n                    await bot1.chat('hello!!!!!!!!!!!');\n                    await bot1.chat('/gamerule doMobSpawning false');\n                    await bot1.chat('/gamerule randomTickSpeed 0');\n                    \n                    await bot3.chat('/gamemode survival');\n                    await bot0.chat('/gamemode survival');\n                    await bot1.chat('/forceload add 4281 1129');\n                    await bot4.chat('/setblock 4284 67 1126 minecraft:barrier');\n                    await bot4.chat('/gamemode spectator');\n                    await bot4.chat('/tp @p 4284 68 1126 -90 90');\n                await bot1.chat('/fill 4282 63 1124 4286 63 1128 minecraft:glass');await bot1.chat('/fill 4281 64 1123 4286 65 1128 minecraft:air');await bot1.chat('/setblock 4285 65 1125 minecraft:bricks');await bot1.chat('/setblock 4284 65 1125 minecraft:oak_planks');await bot1.chat('/setblock 4283 65 1125 minecraft:sponge');await bot1.chat('/setblock 4285 64 1125 minecraft:bricks');await bot1.chat('/setblock 4284 64 1125 minecraft:pumpkin');await bot1.chat('/setblock 4283 64 1125 minecraft:clay');await bot0.chat('/tp @p 4283.9 65 1116.19 103.96 6.5 ');await bot0.chat('/give @p bricks 4');await bot0.chat('/give @p sponge 5');await bot0.chat('/give @p oak_planks 2');await bot0.chat('/give @p clay 1');await bot0.chat('/give @p pumpkin 3');await bot1.chat('/tp @p 4283.35 65 1121.34 193.53 6.19 ');await bot1.chat('/give @p pumpkin 1');await bot1.chat('/give @p oak_planks 2');await bot1.chat('/give @p sponge 2');await bot1.chat('/give @p clay 2');await bot2.chat('/tp @p 4283.68 65 1121.82 185.5 -0.94 ');await bot2.chat('/give @p clay 2');await bot2.chat('/give @p bricks 3');await bot2.chat('/give @p oak_planks 3');await bot3.chat('/tp @p 4285.81 65 1116.01 207.38 2.75 ');await bot3.chat('/give @p clay 1');await bot3.chat('/give @p sponge 2');await bot3.chat('/give @p bricks 2');",
    "obs_command": [
        [
            "\n                    await bot4.chat('/setblock 4278 63 1126 minecraft:barrier');\n                    await bot4.chat('/tp @p 4278 64 1126 -90 0');\n                "
        ],
        [
            "\n                    await bot4.chat('/setblock 4284 63 1132 minecraft:barrier');\n                    await bot4.chat('/tp @p 4284 64 1132 -180 0');\n                "
        ],
        [
            "\n                    await bot4.chat('/tp @p 4284 68 1126 -90 90');\n                "
        ],
        [
            "await bot1.chat('/fill 4281 64 1123 4286 65 1128 minecraft:air');"
        ]
    ],
    "variant": 100001,
    "actions": [
        [],
        []
    ],
    "done_input": [
        [
            "bricks",
            4285,
            65,
            1125
        ],
        [
            "oak_planks",
            4284,
            65,
            1125
        ],
        [
            "sponge",
            4283,
            65,
            1125
        ],
        [
            "bricks",
            4285,
            64,
            1125
        ],
        [
            "pumpkin",
            4284,
            64,
            1125
        ],
        [
            "clay",
            4283,
            64,
            1125
        ]
    ],
    "bot0": {
        "location": [
            4283.9,
            65,
            1116.19
        ],
        "rotation": [
            103.96,
            6.5
        ],
        "inventory": {
            "bricks": 4,
            "sponge": 5,
            "oak_planks": 2,
            "clay": 1,
            "pumpkin": 3
        }
    },
    "bot1": {
        "location": [
            4283.35,
            65,
            1121.34
        ],
        "rotation": [
            193.53,
            6.19
        ],
        "inventory": {
            "pumpkin": 1,
            "oak_planks": 2,
            "sponge": 2,
            "clay": 2
        }
    },
    "bot2": {
        "location": [
            4283.68,
            65,
            1121.82
        ],
        "rotation": [
            185.5,
            -0.94
        ],
        "inventory": {
            "clay": 2,
            "bricks": 3,
            "oak_planks": 3
        }
    },
    "bot3": {
        "location": [
            4285.81,
            65,
            1116.01
        ],
        "rotation": [
            207.38,
            2.75
        ],
        "inventory": {
            "clay": 1,
            "sponge": 2,
            "bricks": 2
        }
    },
    "item_spots": {},
    "variants_config": {
        "agent_counts": [
            4
        ],
        "background": [
            "minecraft:glass"
        ],
        "playground_location": {
            "name": "swamp",
            "x": [
                4282,
                4286
            ],
            "z": [
                1124,
                1128
            ],
            "y": 64,
            "bot_range": [
                [
                    4283,
                    4286
                ],
                [
                    1116,
                    1122
                ],
                65
            ],
            "center": [
                4284,
                64,
                1126
            ]
        },
        "base_shape": [
            [
                3,
                1,
                2
            ]
        ],
        "block_type": [
            "bricks",
            "oak_planks",
            "sponge",
            "bricks",
            "pumpkin",
            "clay"
        ],
        "placement_shape": [
            [
                2,
                1,
                0
            ],
            [
                1,
                1,
                0
            ],
            [
                0,
                1,
                0
            ],
            [
                2,
                0,
                0
            ],
            [
                1,
                0,
                0
            ],
            [
                0,
                0,
                0
            ]
        ],
        "block_count": 6,
        "placement_shape_number": [
            5,
            4,
            3,
            2,
            1,
            0
        ]
    },
    "bot_list": [
        "bot0",
        "bot1",
        "bot2",
        "bot3"
    ],
    "center_position": [
        4284,
        64,
        1126
    ]
}