{
    "command": "\n                    await bot1.chat('hello!!!!!!!!!!!');\n                    await bot1.chat('/gamerule doMobSpawning false');\n                    await bot1.chat('/gamerule randomTickSpeed 0');\n                    \n                    await bot3.chat('/gamemode spectator');\n                    await bot3.chat('/tp @p 10 10 10');\n                    await bot1.chat('/forceload add 4281 1129');\n                    await bot4.chat('/setblock 4284 67 1126 minecraft:barrier');\n                    await bot4.chat('/gamemode spectator');\n                    await bot4.chat('/tp @p 4284 68 1126 -90 90');\n                await bot1.chat('/fill 4282 63 1124 4286 63 1128 minecraft:glowstone');await bot1.chat('/fill 4281 64 1123 4286 65 1128 minecraft:air');await bot1.chat('/setblock 4284 65 1126 minecraft:grass_block');await bot1.chat('/setblock 4284 64 1126 minecraft:stone');await bot1.chat('/setblock 4283 64 1126 minecraft:sponge');await bot1.chat('/setblock 4284 64 1125 minecraft:birch_log');await bot1.chat('/setblock 4283 64 1125 minecraft:birch_log');await bot1.chat('/tp @p 4283.17 65 1121.53 196.57 9.83 ');await bot1.chat('/give @p stone 3');await bot1.chat('/give @p birch_log 6');await bot1.chat('/give @p grass_block 4');await bot1.chat('/give @p sponge 3');await bot2.chat('/tp @p 4283.02 65 1117.13 150.69 0.69 ');await bot2.chat('/give @p sponge 2');await bot2.chat('/give @p birch_log 3');await bot2.chat('/give @p grass_block 3');",
    "obs_command": [
        [
            "\n                    await bot4.chat('/setblock 4278 63 1126 minecraft:barrier');\n                    await bot4.chat('/tp @p 4278 64 1126 -90 0');\n                "
        ],
        [
            "\n                    await bot4.chat('/setblock 4284 63 1132 minecraft:barrier');\n                    await bot4.chat('/tp @p 4284 64 1132 -180 0');\n                "
        ],
        [
            "\n                    await bot4.chat('/tp @p 4284 68 1126 -90 90');\n                "
        ],
        [
            "await bot1.chat('/fill 4281 64 1123 4286 65 1128 minecraft:air');"
        ]
    ],
    "variant": 100025,
    "actions": [
        [],
        [],
        []
    ],
    "done_input": [
        [
            "grass_block",
            4284,
            65,
            1126
        ],
        [
            "stone",
            4284,
            64,
            1126
        ],
        [
            "sponge",
            4283,
            64,
            1126
        ],
        [
            "birch_log",
            4284,
            64,
            1125
        ],
        [
            "birch_log",
            4283,
            64,
            1125
        ]
    ],
    "bot1": {
        "location": [
            4283.17,
            65,
            1121.53
        ],
        "rotation": [
            196.57,
            9.83
        ],
        "inventory": {
            "stone": 3,
            "birch_log": 6,
            "grass_block": 4,
            "sponge": 3
        }
    },
    "bot2": {
        "location": [
            4283.02,
            65,
            1117.13
        ],
        "rotation": [
            150.69,
            0.69
        ],
        "inventory": {
            "sponge": 2,
            "birch_log": 3,
            "grass_block": 3
        }
    },
    "item_spots": {},
    "variants_config": {
        "agent_counts": [
            2
        ],
        "background": [
            "minecraft:glowstone"
        ],
        "playground_location": {
            "name": "swamp",
            "x": [
                4282,
                4286
            ],
            "z": [
                1124,
                1128
            ],
            "y": 64,
            "bot_range": [
                [
                    4283,
                    4286
                ],
                [
                    1116,
                    1122
                ],
                65
            ],
            "center": [
                4284,
                64,
                1126
            ]
        },
        "base_shape": [
            [
                2,
                2,
                2
            ]
        ],
        "block_type": [
            "grass_block",
            "stone",
            "sponge",
            "birch_log",
            "birch_log"
        ],
        "placement_shape": [
            [
                1,
                1,
                1
            ],
            [
                1,
                0,
                1
            ],
            [
                0,
                0,
                1
            ],
            [
                1,
                0,
                0
            ],
            [
                0,
                0,
                0
            ]
        ],
        "block_count": 5,
        "placement_shape_number": [
            7,
            3,
            2,
            1,
            0
        ]
    },
    "bot_list": [
        "bot1",
        "bot2"
    ],
    "center_position": [
        4284,
        64,
        1126
    ]
}