{
    "command": "\n                    await bot1.chat('hello!!!!!!!!!!!');\n                    await bot1.chat('/gamerule doMobSpawning false');\n                    await bot1.chat('/gamerule randomTickSpeed 0');\n                    \n                    await bot3.chat('/gamemode spectator');\n                    await bot3.chat('/tp @p 10 10 10');\n                    await bot1.chat('/forceload add 4258 164');\n                    await bot4.chat('/setblock 4261 77 161 minecraft:barrier');\n                    await bot4.chat('/gamemode spectator');\n                    await bot4.chat('/tp @p 4261 78 161 -90 90');\n                await bot1.chat('/fill 4259 73 159 4263 73 163 minecraft:hay_block');await bot1.chat('/fill 4258 74 158 4263 75 163 minecraft:air');await bot1.chat('/setblock 4261 75 161 minecraft:gold_ore');await bot1.chat('/setblock 4261 74 161 minecraft:sponge');await bot1.chat('/setblock 4260 74 161 minecraft:gold_ore');await bot1.chat('/setblock 4261 74 160 minecraft:clay');await bot1.chat('/setblock 4260 74 160 minecraft:gold_ore');await bot1.chat('/tp @p 4264.94 75 159.66 104.09 -9.29 ');await bot1.chat('/give @p sponge 1');await bot1.chat('/give @p gold_ore 6');await bot2.chat('/tp @p 4263.78 75 155.3 332.97 9.44 ');await bot2.chat('/give @p gold_ore 5');await bot2.chat('/give @p clay 5');",
    "obs_command": [
        [
            "\n                    await bot4.chat('/setblock 4255 73 161 minecraft:barrier');\n                    await bot4.chat('/tp @p 4255 74 161 -90 0');\n                "
        ],
        [
            "\n                    await bot4.chat('/setblock 4261 73 167 minecraft:barrier');\n                    await bot4.chat('/tp @p 4261 74 167 -180 0');\n                "
        ],
        [
            "\n                    await bot4.chat('/tp @p 4261 78 161 -90 90');\n                "
        ],
        [
            "await bot1.chat('/fill 4258 74 158 4263 75 163 minecraft:air');"
        ]
    ],
    "variant": 100041,
    "actions": [
        [],
        [],
        []
    ],
    "done_input": [
        [
            "gold_ore",
            4261,
            75,
            161
        ],
        [
            "sponge",
            4261,
            74,
            161
        ],
        [
            "gold_ore",
            4260,
            74,
            161
        ],
        [
            "clay",
            4261,
            74,
            160
        ],
        [
            "gold_ore",
            4260,
            74,
            160
        ]
    ],
    "bot1": {
        "location": [
            4264.94,
            75,
            159.66
        ],
        "rotation": [
            104.09,
            -9.29
        ],
        "inventory": {
            "sponge": 1,
            "gold_ore": 6
        }
    },
    "bot2": {
        "location": [
            4263.78,
            75,
            155.3
        ],
        "rotation": [
            332.97,
            9.44
        ],
        "inventory": {
            "gold_ore": 5,
            "clay": 5
        }
    },
    "item_spots": {},
    "variants_config": {
        "agent_counts": [
            2
        ],
        "background": [
            "minecraft:hay_block"
        ],
        "playground_location": {
            "name": "desert_villege",
            "x": [
                4259,
                4263
            ],
            "z": [
                159,
                163
            ],
            "y": 74,
            "bot_range": [
                [
                    4263,
                    4265
                ],
                [
                    155,
                    163
                ],
                75
            ],
            "center": [
                4261,
                74,
                161
            ]
        },
        "base_shape": [
            [
                2,
                2,
                2
            ]
        ],
        "block_type": [
            "gold_ore",
            "sponge",
            "gold_ore",
            "clay",
            "gold_ore"
        ],
        "placement_shape": [
            [
                1,
                1,
                1
            ],
            [
                1,
                0,
                1
            ],
            [
                0,
                0,
                1
            ],
            [
                1,
                0,
                0
            ],
            [
                0,
                0,
                0
            ]
        ],
        "block_count": 5,
        "placement_shape_number": [
            7,
            3,
            2,
            1,
            0
        ]
    },
    "bot_list": [
        "bot1",
        "bot2"
    ],
    "center_position": [
        4261,
        74,
        161
    ]
}