{
    "command": "\n                    await bot1.chat('hello!!!!!!!!!!!');\n                    await bot1.chat('/gamerule doMobSpawning false');\n                    await bot1.chat('/gamerule randomTickSpeed 0');\n                    \n                    await bot3.chat('/gamemode spectator');\n                    await bot3.chat('/tp @p 10 10 10');\n                    await bot1.chat('/forceload add 220 131');\n                    await bot4.chat('/setblock 223 73 128 minecraft:barrier');\n                    await bot4.chat('/gamemode spectator');\n                    await bot4.chat('/tp @p 223 74 128 -90 90');\n                await bot1.chat('/fill 221 69 126 225 69 130 minecraft:stone');await bot1.chat('/fill 220 70 125 225 71 130 minecraft:air');await bot1.chat('/setblock 223 71 128 minecraft:coal_ore');await bot1.chat('/setblock 222 71 128 minecraft:bricks');await bot1.chat('/setblock 223 70 128 minecraft:bricks');await bot1.chat('/setblock 222 70 128 minecraft:sea_lantern');await bot1.chat('/setblock 223 70 127 minecraft:stone');await bot1.chat('/setblock 222 70 127 minecraft:stone');await bot1.chat('/tp @p 227.11 72 127.52 259.78 -3.56 ');await bot1.chat('/give @p bricks 2');await bot1.chat('/give @p stone 1');await bot1.chat('/give @p coal_ore 6');await bot2.chat('/tp @p 227.97 72 129.94 175.64 4.67 ');await bot2.chat('/give @p sea_lantern 4');await bot2.chat('/give @p stone 3');await bot2.chat('/give @p bricks 6');await bot2.chat('/give @p coal_ore 3');",
    "obs_command": [
        [
            "\n                    await bot4.chat('/setblock 217 69 128 minecraft:barrier');\n                    await bot4.chat('/tp @p 217 70 128 -90 0');\n                "
        ],
        [
            "\n                    await bot4.chat('/setblock 223 69 134 minecraft:barrier');\n                    await bot4.chat('/tp @p 223 70 134 -180 0');\n                "
        ],
        [
            "\n                    await bot4.chat('/tp @p 223 74 128 -90 90');\n                "
        ],
        [
            "await bot1.chat('/fill 220 70 125 225 71 130 minecraft:air');"
        ]
    ],
    "variant": 100042,
    "actions": [
        [],
        [],
        []
    ],
    "done_input": [
        [
            "coal_ore",
            223,
            71,
            128
        ],
        [
            "bricks",
            222,
            71,
            128
        ],
        [
            "bricks",
            223,
            70,
            128
        ],
        [
            "sea_lantern",
            222,
            70,
            128
        ],
        [
            "stone",
            223,
            70,
            127
        ],
        [
            "stone",
            222,
            70,
            127
        ]
    ],
    "bot1": {
        "location": [
            227.11,
            72,
            127.52
        ],
        "rotation": [
            259.78,
            -3.56
        ],
        "inventory": {
            "bricks": 2,
            "stone": 1,
            "coal_ore": 6
        }
    },
    "bot2": {
        "location": [
            227.97,
            72,
            129.94
        ],
        "rotation": [
            175.64,
            4.67
        ],
        "inventory": {
            "sea_lantern": 4,
            "stone": 3,
            "bricks": 6,
            "coal_ore": 3
        }
    },
    "item_spots": {},
    "variants_config": {
        "agent_counts": [
            2
        ],
        "background": [
            "minecraft:stone"
        ],
        "playground_location": {
            "name": "villege",
            "x": [
                221,
                225
            ],
            "z": [
                126,
                130
            ],
            "y": 70,
            "bot_range": [
                [
                    226,
                    229
                ],
                [
                    125,
                    131
                ],
                72
            ],
            "center": [
                223,
                70,
                128
            ]
        },
        "base_shape": [
            [
                2,
                2,
                2
            ]
        ],
        "block_type": [
            "coal_ore",
            "bricks",
            "bricks",
            "sea_lantern",
            "stone",
            "stone"
        ],
        "placement_shape": [
            [
                1,
                1,
                1
            ],
            [
                0,
                1,
                1
            ],
            [
                1,
                0,
                1
            ],
            [
                0,
                0,
                1
            ],
            [
                1,
                0,
                0
            ],
            [
                0,
                0,
                0
            ]
        ],
        "block_count": 6,
        "placement_shape_number": [
            7,
            6,
            3,
            2,
            1,
            0
        ]
    },
    "bot_list": [
        "bot1",
        "bot2"
    ],
    "center_position": [
        223,
        70,
        128
    ]
}