{
    "command": "\n                    await bot1.chat('hello!!!!!!!!!!!');\n                    await bot1.chat('/gamerule doMobSpawning false');\n                    await bot1.chat('/gamerule randomTickSpeed 0');\n                    \n                    await bot3.chat('/gamemode spectator');\n                    await bot3.chat('/tp @p 10 10 10');\n                    await bot1.chat('/forceload add 4281 1129');\n                    await bot4.chat('/setblock 4284 67 1126 minecraft:barrier');\n                    await bot4.chat('/gamemode spectator');\n                    await bot4.chat('/tp @p 4284 68 1126 -90 90');\n                await bot1.chat('/fill 4282 63 1124 4286 63 1128 minecraft:glowstone');await bot1.chat('/fill 4281 64 1123 4286 65 1128 minecraft:air');await bot1.chat('/setblock 4284 65 1126 minecraft:sandstone');await bot1.chat('/setblock 4283 65 1126 minecraft:birch_log');await bot1.chat('/setblock 4284 65 1125 minecraft:bricks');await bot1.chat('/setblock 4284 64 1127 minecraft:purple_wool');await bot1.chat('/setblock 4283 64 1127 minecraft:purple_wool');await bot1.chat('/setblock 4284 64 1126 minecraft:stone');await bot1.chat('/setblock 4283 64 1126 minecraft:oak_planks');await bot1.chat('/setblock 4284 64 1125 minecraft:dirt');await bot1.chat('/setblock 4283 64 1125 minecraft:sandstone');await bot1.chat('/tp @p 4284.52 65 1118.95 309.07 8.05 ');await bot1.chat('/give @p purple_wool 1');await bot1.chat('/give @p sandstone 5');await bot1.chat('/give @p stone 1');await bot1.chat('/give @p bricks 1');await bot2.chat('/tp @p 4285.87 65 1118.52 103.88 6.47 ');await bot2.chat('/give @p purple_wool 6');await bot2.chat('/give @p dirt 4');await bot2.chat('/give @p oak_planks 2');await bot2.chat('/give @p birch_log 5');await bot2.chat('/give @p stone 2');await bot2.chat('/give @p bricks 3');await bot2.chat('/give @p sandstone 6');",
    "obs_command": [
        [
            "\n                    await bot4.chat('/setblock 4278 63 1126 minecraft:barrier');\n                    await bot4.chat('/tp @p 4278 64 1126 -90 0');\n                "
        ],
        [
            "\n                    await bot4.chat('/setblock 4284 63 1132 minecraft:barrier');\n                    await bot4.chat('/tp @p 4284 64 1132 -180 0');\n                "
        ],
        [
            "\n                    await bot4.chat('/tp @p 4284 68 1126 -90 90');\n                "
        ],
        [
            "await bot1.chat('/fill 4281 64 1123 4286 65 1128 minecraft:air');"
        ]
    ],
    "variant": 100046,
    "actions": [
        [],
        [],
        [],
        [],
        []
    ],
    "done_input": [
        [
            "sandstone",
            4284,
            65,
            1126
        ],
        [
            "birch_log",
            4283,
            65,
            1126
        ],
        [
            "bricks",
            4284,
            65,
            1125
        ],
        [
            "purple_wool",
            4284,
            64,
            1127
        ],
        [
            "purple_wool",
            4283,
            64,
            1127
        ],
        [
            "stone",
            4284,
            64,
            1126
        ],
        [
            "oak_planks",
            4283,
            64,
            1126
        ],
        [
            "dirt",
            4284,
            64,
            1125
        ],
        [
            "sandstone",
            4283,
            64,
            1125
        ]
    ],
    "bot1": {
        "location": [
            4284.52,
            65,
            1118.95
        ],
        "rotation": [
            309.07,
            8.05
        ],
        "inventory": {
            "purple_wool": 1,
            "sandstone": 5,
            "stone": 1,
            "bricks": 1
        }
    },
    "bot2": {
        "location": [
            4285.87,
            65,
            1118.52
        ],
        "rotation": [
            103.88,
            6.47
        ],
        "inventory": {
            "purple_wool": 6,
            "dirt": 4,
            "oak_planks": 2,
            "birch_log": 5,
            "stone": 2,
            "bricks": 3,
            "sandstone": 6
        }
    },
    "item_spots": {},
    "variants_config": {
        "agent_counts": [
            2
        ],
        "background": [
            "minecraft:glowstone"
        ],
        "playground_location": {
            "name": "swamp",
            "x": [
                4282,
                4286
            ],
            "z": [
                1124,
                1128
            ],
            "y": 64,
            "bot_range": [
                [
                    4283,
                    4286
                ],
                [
                    1116,
                    1122
                ],
                65
            ],
            "center": [
                4284,
                64,
                1126
            ]
        },
        "base_shape": [
            [
                2,
                3,
                2
            ]
        ],
        "block_type": [
            "sandstone",
            "birch_log",
            "bricks",
            "purple_wool",
            "purple_wool",
            "stone",
            "oak_planks",
            "dirt",
            "sandstone"
        ],
        "placement_shape": [
            [
                1,
                1,
                1
            ],
            [
                0,
                1,
                1
            ],
            [
                1,
                1,
                0
            ],
            [
                1,
                0,
                2
            ],
            [
                0,
                0,
                2
            ],
            [
                1,
                0,
                1
            ],
            [
                0,
                0,
                1
            ],
            [
                1,
                0,
                0
            ],
            [
                0,
                0,
                0
            ]
        ],
        "block_count": 9,
        "placement_shape_number": [
            9,
            8,
            7,
            5,
            4,
            3,
            2,
            1,
            0
        ]
    },
    "bot_list": [
        "bot1",
        "bot2"
    ],
    "center_position": [
        4284,
        64,
        1126
    ]
}