{
    "command": "\n                    await bot1.chat('hello!!!!!!!!!!!');\n                    await bot1.chat('/gamerule doMobSpawning false');\n                    await bot1.chat('/gamerule randomTickSpeed 0');\n                    \n                    await bot3.chat('/gamemode survival');\n                    await bot1.chat('/forceload add 4281 1129');\n                    await bot4.chat('/setblock 4284 67 1126 minecraft:barrier');\n                    await bot4.chat('/gamemode spectator');\n                    await bot4.chat('/tp @p 4284 68 1126 -90 90');\n                await bot1.chat('/fill 4282 63 1124 4286 63 1128 minecraft:glowstone');await bot1.chat('/fill 4281 64 1123 4286 65 1128 minecraft:air');await bot1.chat('/setblock 4284 65 1125 minecraft:clay');await bot1.chat('/setblock 4283 65 1125 minecraft:bricks');await bot1.chat('/setblock 4286 64 1125 minecraft:end_stone');await bot1.chat('/setblock 4285 64 1125 minecraft:end_stone');await bot1.chat('/setblock 4284 64 1125 minecraft:pumpkin');await bot1.chat('/setblock 4283 64 1125 minecraft:end_stone');await bot1.chat('/tp @p 4284.1 65 1119.01 217.68 2.28 ');await bot1.chat('/give @p end_stone 4');await bot1.chat('/give @p bricks 2');await bot1.chat('/give @p pumpkin 1');await bot2.chat('/tp @p 4285.71 65 1118.85 226.27 4.88 ');await bot2.chat('/give @p end_stone 6');await bot2.chat('/give @p clay 5');await bot2.chat('/give @p pumpkin 2');await bot3.chat('/tp @p 4285.04 65 1117.96 283.74 3.96 ');await bot3.chat('/give @p pumpkin 3');await bot3.chat('/give @p clay 3');await bot3.chat('/give @p end_stone 4');await bot3.chat('/give @p bricks 1');",
    "obs_command": [
        [
            "\n                    await bot4.chat('/setblock 4278 63 1126 minecraft:barrier');\n                    await bot4.chat('/tp @p 4278 64 1126 -90 0');\n                "
        ],
        [
            "\n                    await bot4.chat('/setblock 4284 63 1132 minecraft:barrier');\n                    await bot4.chat('/tp @p 4284 64 1132 -180 0');\n                "
        ],
        [
            "\n                    await bot4.chat('/tp @p 4284 68 1126 -90 90');\n                "
        ],
        [
            "await bot1.chat('/fill 4281 64 1123 4286 65 1128 minecraft:air');"
        ]
    ],
    "variant": 100003,
    "actions": [
        [],
        [],
        []
    ],
    "done_input": [
        [
            "clay",
            4284,
            65,
            1125
        ],
        [
            "bricks",
            4283,
            65,
            1125
        ],
        [
            "end_stone",
            4286,
            64,
            1125
        ],
        [
            "end_stone",
            4285,
            64,
            1125
        ],
        [
            "pumpkin",
            4284,
            64,
            1125
        ],
        [
            "end_stone",
            4283,
            64,
            1125
        ]
    ],
    "bot1": {
        "location": [
            4284.1,
            65,
            1119.01
        ],
        "rotation": [
            217.68,
            2.28
        ],
        "inventory": {
            "end_stone": 4,
            "bricks": 2,
            "pumpkin": 1
        }
    },
    "bot2": {
        "location": [
            4285.71,
            65,
            1118.85
        ],
        "rotation": [
            226.27,
            4.88
        ],
        "inventory": {
            "end_stone": 6,
            "clay": 5,
            "pumpkin": 2
        }
    },
    "bot3": {
        "location": [
            4285.04,
            65,
            1117.96
        ],
        "rotation": [
            283.74,
            3.96
        ],
        "inventory": {
            "pumpkin": 3,
            "clay": 3,
            "end_stone": 4,
            "bricks": 1
        }
    },
    "item_spots": {},
    "variants_config": {
        "agent_counts": [
            3
        ],
        "background": [
            "minecraft:glowstone"
        ],
        "playground_location": {
            "name": "swamp",
            "x": [
                4282,
                4286
            ],
            "z": [
                1124,
                1128
            ],
            "y": 64,
            "bot_range": [
                [
                    4283,
                    4286
                ],
                [
                    1116,
                    1122
                ],
                65
            ],
            "center": [
                4284,
                64,
                1126
            ]
        },
        "base_shape": [
            [
                4,
                1,
                2
            ]
        ],
        "block_type": [
            "clay",
            "bricks",
            "end_stone",
            "end_stone",
            "pumpkin",
            "end_stone"
        ],
        "placement_shape": [
            [
                1,
                1,
                0
            ],
            [
                0,
                1,
                0
            ],
            [
                3,
                0,
                0
            ],
            [
                2,
                0,
                0
            ],
            [
                1,
                0,
                0
            ],
            [
                0,
                0,
                0
            ]
        ],
        "block_count": 6,
        "placement_shape_number": [
            5,
            4,
            3,
            2,
            1,
            0
        ]
    },
    "bot_list": [
        "bot1",
        "bot2",
        "bot3"
    ],
    "center_position": [
        4284,
        64,
        1126
    ]
}