{
    "command": "\n                    await bot1.chat('hello!!!!!!!!!!!');\n                    await bot1.chat('/gamerule doMobSpawning false');\n                    await bot1.chat('/gamerule randomTickSpeed 0');\n                    \n                    await bot3.chat('/gamemode spectator');\n                    await bot3.chat('/tp @p 10 10 10');\n                    await bot1.chat('/forceload add 4299 214');\n                    await bot4.chat('/setblock 4302 100 211 minecraft:barrier');\n                    await bot4.chat('/gamemode spectator');\n                    await bot4.chat('/tp @p 4302 101 211 -90 90');\n                await bot1.chat('/fill 4300 96 209 4304 96 213 minecraft:glowstone');await bot1.chat('/fill 4299 97 208 4304 98 213 minecraft:air');await bot1.chat('/setblock 4303 98 210 minecraft:gold_ore');await bot1.chat('/setblock 4302 98 210 minecraft:sponge');await bot1.chat('/setblock 4301 98 210 minecraft:emerald_block');await bot1.chat('/setblock 4303 97 210 minecraft:stone');await bot1.chat('/setblock 4302 97 210 minecraft:stone');await bot1.chat('/setblock 4301 97 210 minecraft:dirt');await bot1.chat('/tp @p 4305.27 98 209.05 318.76 1.26 ');await bot1.chat('/give @p stone 8');await bot1.chat('/give @p dirt 5');await bot1.chat('/give @p emerald_block 3');await bot1.chat('/give @p gold_ore 1');await bot2.chat('/tp @p 4306.95 98 210.22 66.98 -3.22 ');await bot2.chat('/give @p stone 3');await bot2.chat('/give @p sponge 4');await bot2.chat('/give @p gold_ore 5');await bot2.chat('/give @p dirt 2');await bot2.chat('/give @p emerald_block 3');",
    "obs_command": [
        [
            "\n                    await bot4.chat('/setblock 4296 96 211 minecraft:barrier');\n                    await bot4.chat('/tp @p 4296 97 211 -90 0');\n                "
        ],
        [
            "\n                    await bot4.chat('/setblock 4302 96 217 minecraft:barrier');\n                    await bot4.chat('/tp @p 4302 97 217 -180 0');\n                "
        ],
        [
            "\n                    await bot4.chat('/tp @p 4302 101 211 -90 90');\n                "
        ],
        [
            "await bot1.chat('/fill 4299 97 208 4304 98 213 minecraft:air');"
        ]
    ],
    "variant": 100005,
    "actions": [
        [],
        [],
        []
    ],
    "done_input": [
        [
            "gold_ore",
            4303,
            98,
            210
        ],
        [
            "sponge",
            4302,
            98,
            210
        ],
        [
            "emerald_block",
            4301,
            98,
            210
        ],
        [
            "stone",
            4303,
            97,
            210
        ],
        [
            "stone",
            4302,
            97,
            210
        ],
        [
            "dirt",
            4301,
            97,
            210
        ]
    ],
    "bot1": {
        "location": [
            4305.27,
            98,
            209.05
        ],
        "rotation": [
            318.76,
            1.26
        ],
        "inventory": {
            "stone": 8,
            "dirt": 5,
            "emerald_block": 3,
            "gold_ore": 1
        }
    },
    "bot2": {
        "location": [
            4306.95,
            98,
            210.22
        ],
        "rotation": [
            66.98,
            -3.22
        ],
        "inventory": {
            "stone": 3,
            "sponge": 4,
            "gold_ore": 5,
            "dirt": 2,
            "emerald_block": 3
        }
    },
    "item_spots": {},
    "variants_config": {
        "agent_counts": [
            2
        ],
        "background": [
            "minecraft:glowstone"
        ],
        "playground_location": {
            "name": "mountain_half",
            "x": [
                4300,
                4304
            ],
            "z": [
                209,
                213
            ],
            "y": 97,
            "bot_range": [
                [
                    4305,
                    4307
                ],
                [
                    209,
                    211
                ],
                98
            ],
            "center": [
                4302,
                97,
                211
            ]
        },
        "base_shape": [
            [
                3,
                1,
                2
            ]
        ],
        "block_type": [
            "gold_ore",
            "sponge",
            "emerald_block",
            "stone",
            "stone",
            "dirt"
        ],
        "placement_shape": [
            [
                2,
                1,
                0
            ],
            [
                1,
                1,
                0
            ],
            [
                0,
                1,
                0
            ],
            [
                2,
                0,
                0
            ],
            [
                1,
                0,
                0
            ],
            [
                0,
                0,
                0
            ]
        ],
        "block_count": 6,
        "placement_shape_number": [
            5,
            4,
            3,
            2,
            1,
            0
        ]
    },
    "bot_list": [
        "bot1",
        "bot2"
    ],
    "center_position": [
        4302,
        97,
        211
    ]
}