{
    "command": "\n                    await bot1.chat('hello!!!!!!!!!!!');\n                    await bot1.chat('/gamerule doMobSpawning false');\n                    await bot1.chat('/gamerule randomTickSpeed 0');\n                    \n                    await bot3.chat('/gamemode spectator');\n                    await bot3.chat('/tp @p 10 10 10');\n                    await bot1.chat('/forceload add 11668 8491');\n                    await bot4.chat('/setblock 11671 109 8488 minecraft:barrier');\n                    await bot4.chat('/gamemode spectator');\n                    await bot4.chat('/tp @p 11671 110 8488 -90 90');\n                await bot1.chat('/fill 11669 105 8486 11673 105 8490 minecraft:obsidian');await bot1.chat('/fill 11668 106 8485 11673 107 8490 minecraft:air');await bot1.chat('/setblock 11670 107 8488 minecraft:bricks');await bot1.chat('/setblock 11671 106 8489 minecraft:orange_concrete');await bot1.chat('/setblock 11670 106 8489 minecraft:sponge');await bot1.chat('/setblock 11671 106 8488 minecraft:emerald_block');await bot1.chat('/setblock 11670 106 8488 minecraft:sponge');await bot1.chat('/tp @p 11670.24 108 8494.82 329.54 3.04 ');await bot1.chat('/give @p orange_concrete 3');await bot1.chat('/give @p sponge 3');await bot1.chat('/give @p bricks 4');await bot2.chat('/tp @p 11669.38 108 8495.68 8.76 -9.82 ');await bot2.chat('/give @p sponge 7');await bot2.chat('/give @p emerald_block 5');await bot2.chat('/give @p bricks 3');await bot2.chat('/give @p orange_concrete 1');",
    "obs_command": [
        [
            "\n                    await bot4.chat('/setblock 11665 105 8488 minecraft:barrier');\n                    await bot4.chat('/tp @p 11665 106 8488 -90 0');\n                "
        ],
        [
            "\n                    await bot4.chat('/setblock 11671 105 8494 minecraft:barrier');\n                    await bot4.chat('/tp @p 11671 106 8494 -180 0');\n                "
        ],
        [
            "\n                    await bot4.chat('/tp @p 11671 110 8488 -90 90');\n                "
        ],
        [
            "await bot1.chat('/fill 11668 106 8485 11673 107 8490 minecraft:air');"
        ]
    ],
    "variant": 100009,
    "actions": [
        [],
        [],
        []
    ],
    "done_input": [
        [
            "bricks",
            11670,
            107,
            8488
        ],
        [
            "orange_concrete",
            11671,
            106,
            8489
        ],
        [
            "sponge",
            11670,
            106,
            8489
        ],
        [
            "emerald_block",
            11671,
            106,
            8488
        ],
        [
            "sponge",
            11670,
            106,
            8488
        ]
    ],
    "bot1": {
        "location": [
            11670.24,
            108,
            8494.82
        ],
        "rotation": [
            329.54,
            3.04
        ],
        "inventory": {
            "orange_concrete": 3,
            "sponge": 3,
            "bricks": 4
        }
    },
    "bot2": {
        "location": [
            11669.38,
            108,
            8495.68
        ],
        "rotation": [
            8.76,
            -9.82
        ],
        "inventory": {
            "sponge": 7,
            "emerald_block": 5,
            "bricks": 3,
            "orange_concrete": 1
        }
    },
    "item_spots": {},
    "variants_config": {
        "agent_counts": [
            2
        ],
        "background": [
            "minecraft:obsidian"
        ],
        "playground_location": {
            "name": "snow_mountain",
            "x": [
                11669,
                11673
            ],
            "z": [
                8486,
                8490
            ],
            "y": 106,
            "bot_range": [
                [
                    11668,
                    11673
                ],
                [
                    8494,
                    8496
                ],
                108
            ],
            "center": [
                11671,
                106,
                8488
            ]
        },
        "base_shape": [
            [
                2,
                3,
                2
            ]
        ],
        "block_type": [
            "bricks",
            "orange_concrete",
            "sponge",
            "emerald_block",
            "sponge"
        ],
        "placement_shape": [
            [
                0,
                1,
                1
            ],
            [
                1,
                0,
                2
            ],
            [
                0,
                0,
                2
            ],
            [
                1,
                0,
                1
            ],
            [
                0,
                0,
                1
            ]
        ],
        "block_count": 5,
        "placement_shape_number": [
            8,
            5,
            4,
            3,
            2
        ]
    },
    "bot_list": [
        "bot1",
        "bot2"
    ],
    "center_position": [
        11671,
        106,
        8488
    ]
}