{
    "command": "\n                    await bot1.chat('hello!!!!!!!!!!!');\n                    await bot1.chat('/gamerule doMobSpawning false');\n                    await bot1.chat('/gamerule randomTickSpeed 0');\n                    \n                    await bot3.chat('/gamemode spectator');\n                    await bot3.chat('/tp @p 10 10 10');\n                    await bot1.chat('/forceload add 4281 1129');\n                    await bot4.chat('/setblock 4284 67 1126 minecraft:barrier');\n                    await bot4.chat('/gamemode spectator');\n                    await bot4.chat('/tp @p 4284 68 1126 -90 90');\n                await bot1.chat('/fill 4282 63 1124 4286 63 1128 minecraft:glass');await bot1.chat('/fill 4281 64 1123 4286 65 1128 minecraft:air');await bot1.chat('/setblock 4283 65 1125 minecraft:coal_ore');await bot1.chat('/setblock 4286 64 1125 minecraft:dirt');await bot1.chat('/setblock 4285 64 1125 minecraft:pumpkin');await bot1.chat('/setblock 4284 64 1125 minecraft:emerald_block');await bot1.chat('/setblock 4283 64 1125 minecraft:orange_concrete');await bot1.chat('/tp @p 4285.01 65 1118.5 49.2 -3.13 ');await bot1.chat('/give @p dirt 4');await bot1.chat('/give @p orange_concrete 4');await bot1.chat('/give @p coal_ore 2');await bot2.chat('/tp @p 4284.32 65 1121.47 229.95 -4.1 ');await bot2.chat('/give @p pumpkin 2');await bot2.chat('/give @p emerald_block 1');await bot2.chat('/give @p orange_concrete 2');await bot2.chat('/give @p dirt 1');",
    "obs_command": [
        [
            "\n                    await bot4.chat('/setblock 4278 63 1126 minecraft:barrier');\n                    await bot4.chat('/tp @p 4278 64 1126 -90 0');\n                "
        ],
        [
            "\n                    await bot4.chat('/setblock 4284 63 1132 minecraft:barrier');\n                    await bot4.chat('/tp @p 4284 64 1132 -180 0');\n                "
        ],
        [
            "\n                    await bot4.chat('/tp @p 4284 68 1126 -90 90');\n                "
        ],
        [
            "await bot1.chat('/fill 4281 64 1123 4286 65 1128 minecraft:air');"
        ]
    ],
    "variant": 100011,
    "actions": [
        [],
        [],
        []
    ],
    "done_input": [
        [
            "coal_ore",
            4283,
            65,
            1125
        ],
        [
            "dirt",
            4286,
            64,
            1125
        ],
        [
            "pumpkin",
            4285,
            64,
            1125
        ],
        [
            "emerald_block",
            4284,
            64,
            1125
        ],
        [
            "orange_concrete",
            4283,
            64,
            1125
        ]
    ],
    "bot1": {
        "location": [
            4285.01,
            65,
            1118.5
        ],
        "rotation": [
            49.2,
            -3.13
        ],
        "inventory": {
            "dirt": 4,
            "orange_concrete": 4,
            "coal_ore": 2
        }
    },
    "bot2": {
        "location": [
            4284.32,
            65,
            1121.47
        ],
        "rotation": [
            229.95,
            -4.1
        ],
        "inventory": {
            "pumpkin": 2,
            "emerald_block": 1,
            "orange_concrete": 2,
            "dirt": 1
        }
    },
    "item_spots": {},
    "variants_config": {
        "agent_counts": [
            2
        ],
        "background": [
            "minecraft:glass"
        ],
        "playground_location": {
            "name": "swamp",
            "x": [
                4282,
                4286
            ],
            "z": [
                1124,
                1128
            ],
            "y": 64,
            "bot_range": [
                [
                    4283,
                    4286
                ],
                [
                    1116,
                    1122
                ],
                65
            ],
            "center": [
                4284,
                64,
                1126
            ]
        },
        "base_shape": [
            [
                4,
                1,
                2
            ]
        ],
        "block_type": [
            "coal_ore",
            "dirt",
            "pumpkin",
            "emerald_block",
            "orange_concrete"
        ],
        "placement_shape": [
            [
                0,
                1,
                0
            ],
            [
                3,
                0,
                0
            ],
            [
                2,
                0,
                0
            ],
            [
                1,
                0,
                0
            ],
            [
                0,
                0,
                0
            ]
        ],
        "block_count": 5,
        "placement_shape_number": [
            4,
            3,
            2,
            1,
            0
        ]
    },
    "bot_list": [
        "bot1",
        "bot2"
    ],
    "center_position": [
        4284,
        64,
        1126
    ]
}