{
    "command": "\n                    await bot1.chat('hello!!!!!!!!!!!');\n                    await bot1.chat('/gamerule doMobSpawning false');\n                    await bot1.chat('/gamerule randomTickSpeed 0');\n                    \n                    await bot3.chat('/gamemode spectator');\n                    await bot3.chat('/tp @p 10 10 10');\n                    await bot1.chat('/forceload add 220 131');\n                    await bot4.chat('/setblock 223 73 128 minecraft:barrier');\n                    await bot4.chat('/gamemode spectator');\n                    await bot4.chat('/tp @p 223 74 128 -90 90');\n                await bot1.chat('/fill 221 69 126 225 69 130 minecraft:cyan_concrete');await bot1.chat('/fill 220 70 125 225 71 130 minecraft:air');await bot1.chat('/setblock 222 71 128 minecraft:dirt');await bot1.chat('/setblock 223 71 127 minecraft:purple_wool');await bot1.chat('/setblock 222 70 128 minecraft:sandstone');await bot1.chat('/setblock 223 70 127 minecraft:birch_log');await bot1.chat('/setblock 222 70 127 minecraft:dirt');await bot1.chat('/tp @p 228.35 72 125.54 309.91 2.41 ');await bot1.chat('/give @p sandstone 3');await bot1.chat('/give @p dirt 4');await bot1.chat('/give @p birch_log 2');await bot2.chat('/tp @p 228.75 72 130.95 298.9 -9.78 ');await bot2.chat('/give @p birch_log 4');await bot2.chat('/give @p purple_wool 4');await bot2.chat('/give @p dirt 4');await bot2.chat('/give @p sandstone 1');",
    "obs_command": [
        [
            "\n                    await bot4.chat('/setblock 217 69 128 minecraft:barrier');\n                    await bot4.chat('/tp @p 217 70 128 -90 0');\n                "
        ],
        [
            "\n                    await bot4.chat('/setblock 223 69 134 minecraft:barrier');\n                    await bot4.chat('/tp @p 223 70 134 -180 0');\n                "
        ],
        [
            "\n                    await bot4.chat('/tp @p 223 74 128 -90 90');\n                "
        ],
        [
            "await bot1.chat('/fill 220 70 125 225 71 130 minecraft:air');"
        ]
    ],
    "variant": 100012,
    "actions": [
        [],
        [],
        []
    ],
    "done_input": [
        [
            "dirt",
            222,
            71,
            128
        ],
        [
            "purple_wool",
            223,
            71,
            127
        ],
        [
            "sandstone",
            222,
            70,
            128
        ],
        [
            "birch_log",
            223,
            70,
            127
        ],
        [
            "dirt",
            222,
            70,
            127
        ]
    ],
    "bot1": {
        "location": [
            228.35,
            72,
            125.54
        ],
        "rotation": [
            309.91,
            2.41
        ],
        "inventory": {
            "sandstone": 3,
            "dirt": 4,
            "birch_log": 2
        }
    },
    "bot2": {
        "location": [
            228.75,
            72,
            130.95
        ],
        "rotation": [
            298.9,
            -9.78
        ],
        "inventory": {
            "birch_log": 4,
            "purple_wool": 4,
            "dirt": 4,
            "sandstone": 1
        }
    },
    "item_spots": {},
    "variants_config": {
        "agent_counts": [
            2
        ],
        "background": [
            "minecraft:cyan_concrete"
        ],
        "playground_location": {
            "name": "villege",
            "x": [
                221,
                225
            ],
            "z": [
                126,
                130
            ],
            "y": 70,
            "bot_range": [
                [
                    226,
                    229
                ],
                [
                    125,
                    131
                ],
                72
            ],
            "center": [
                223,
                70,
                128
            ]
        },
        "base_shape": [
            [
                2,
                2,
                2
            ]
        ],
        "block_type": [
            "dirt",
            "purple_wool",
            "sandstone",
            "birch_log",
            "dirt"
        ],
        "placement_shape": [
            [
                0,
                1,
                1
            ],
            [
                1,
                1,
                0
            ],
            [
                0,
                0,
                1
            ],
            [
                1,
                0,
                0
            ],
            [
                0,
                0,
                0
            ]
        ],
        "block_count": 5,
        "placement_shape_number": [
            6,
            5,
            2,
            1,
            0
        ]
    },
    "bot_list": [
        "bot1",
        "bot2"
    ],
    "center_position": [
        223,
        70,
        128
    ]
}