{
    "command": "\n                    await bot1.chat('hello!!!!!!!!!!!');\n                    await bot1.chat('/gamerule doMobSpawning false');\n                    await bot1.chat('/gamerule randomTickSpeed 0');\n                    \n                    await bot3.chat('/gamemode spectator');\n                    await bot3.chat('/tp @p 10 10 10');\n                    await bot1.chat('/forceload add 11668 8491');\n                    await bot4.chat('/setblock 11671 109 8488 minecraft:barrier');\n                    await bot4.chat('/gamemode spectator');\n                    await bot4.chat('/tp @p 11671 110 8488 -90 90');\n                await bot1.chat('/fill 11669 105 8486 11673 105 8490 minecraft:obsidian');await bot1.chat('/fill 11668 106 8485 11673 107 8490 minecraft:air');await bot1.chat('/setblock 11671 107 8488 minecraft:bricks');await bot1.chat('/setblock 11671 106 8488 minecraft:orange_concrete');await bot1.chat('/setblock 11670 106 8488 minecraft:sponge');await bot1.chat('/setblock 11671 106 8487 minecraft:emerald_block');await bot1.chat('/setblock 11670 106 8487 minecraft:sponge');await bot1.chat('/tp @p 11670.64 108 8495.91 258.83 4.86 ');await bot1.chat('/give @p orange_concrete 1');await bot1.chat('/give @p sponge 5');await bot1.chat('/give @p bricks 3');await bot1.chat('/give @p emerald_block 3');await bot2.chat('/tp @p 11670.01 108 8494.55 3.31 6.84 ');await bot2.chat('/give @p sponge 6');await bot2.chat('/give @p emerald_block 4');await bot2.chat('/give @p bricks 3');await bot2.chat('/give @p orange_concrete 1');",
    "obs_command": [
        [
            "\n                    await bot4.chat('/setblock 11665 105 8488 minecraft:barrier');\n                    await bot4.chat('/tp @p 11665 106 8488 -90 0');\n                "
        ],
        [
            "\n                    await bot4.chat('/setblock 11671 105 8494 minecraft:barrier');\n                    await bot4.chat('/tp @p 11671 106 8494 -180 0');\n                "
        ],
        [
            "\n                    await bot4.chat('/tp @p 11671 110 8488 -90 90');\n                "
        ],
        [
            "await bot1.chat('/fill 11668 106 8485 11673 107 8490 minecraft:air');"
        ]
    ],
    "variant": 100009,
    "actions": [
        [],
        [],
        []
    ],
    "done_input": [
        [
            "bricks",
            11671,
            107,
            8488
        ],
        [
            "orange_concrete",
            11671,
            106,
            8488
        ],
        [
            "sponge",
            11670,
            106,
            8488
        ],
        [
            "emerald_block",
            11671,
            106,
            8487
        ],
        [
            "sponge",
            11670,
            106,
            8487
        ]
    ],
    "bot1": {
        "location": [
            11670.64,
            108,
            8495.91
        ],
        "rotation": [
            258.83,
            4.86
        ],
        "inventory": {
            "orange_concrete": 1,
            "sponge": 5,
            "bricks": 3,
            "emerald_block": 3
        }
    },
    "bot2": {
        "location": [
            11670.01,
            108,
            8494.55
        ],
        "rotation": [
            3.31,
            6.84
        ],
        "inventory": {
            "sponge": 6,
            "emerald_block": 4,
            "bricks": 3,
            "orange_concrete": 1
        }
    },
    "item_spots": {},
    "variants_config": {
        "agent_counts": [
            2
        ],
        "background": [
            "minecraft:obsidian"
        ],
        "playground_location": {
            "name": "snow_mountain",
            "x": [
                11669,
                11673
            ],
            "z": [
                8486,
                8490
            ],
            "y": 106,
            "bot_range": [
                [
                    11668,
                    11673
                ],
                [
                    8494,
                    8496
                ],
                108
            ],
            "center": [
                11671,
                106,
                8488
            ]
        },
        "base_shape": [
            [
                2,
                2,
                2
            ]
        ],
        "block_type": [
            "bricks",
            "orange_concrete",
            "sponge",
            "emerald_block",
            "sponge"
        ],
        "placement_shape": [
            [
                1,
                1,
                1
            ],
            [
                1,
                0,
                1
            ],
            [
                0,
                0,
                1
            ],
            [
                1,
                0,
                0
            ],
            [
                0,
                0,
                0
            ]
        ],
        "block_count": 5,
        "placement_shape_number": [
            7,
            3,
            2,
            1,
            0
        ]
    },
    "bot_list": [
        "bot1",
        "bot2"
    ],
    "center_position": [
        11671,
        106,
        8488
    ]
}